<pos><sentence id="59">
  <word wid="0" pos="NNP" lemma="CLIR">CLIR</word>
  <word wid="1" pos="NNPS" lemma="Fellowships">Fellowships</word>
  <word wid="2" pos="NN" lemma="amp">amp</word>
  <word wid="3" pos="NNS" lemma="grant">Grants</word>
  <word wid="4" pos="NNP" lemma="DLF">DLF</word>
  <word wid="5" pos="NNP" lemma="Publications">Publications</word>
  <word wid="6" pos="VB" lemma="join">Join</word>
  <word wid="7" pos="VB" lemma="give">Give</word>
  <word wid="8" pos="JJ" lemma="clir">CLIR</word>
  <word wid="9" pos="NNS" lemma="program">Programs</word>
  <word wid="10" pos="NNP" lemma="Digital">Digital</word>
  <word wid="11" pos="NNP" lemma="Library">Library</word>
  <word wid="12" pos="NNP" lemma="Federation">Federation</word>
  <word wid="13" pos="NNP" lemma="DLF">DLF</word>
  <word wid="14" pos="NNP" lemma="Forum">Forum</word>
  <word wid="15" pos="NNP" lemma="Digital">Digital</word>
  <word wid="16" pos="NNP" lemma="Library">Library</word>
  <word wid="17" pos="IN" lemma="of">of</word>
  <word wid="18" pos="DT" lemma="the">the</word>
  <word wid="19" pos="NNP" lemma="Middle">Middle</word>
  <word wid="20" pos="NNP" lemma="East">East</word>
  <word wid="21" pos="VBG" lemma="digitize">Digitizing</word>
  <word wid="22" pos="JJ" lemma="hidden">Hidden</word>
  <word wid="23" pos="JJ" lemma="special">Special</word>
  <word wid="24" pos="NNS" lemma="collection">Collections</word>
  <word wid="25" pos="CC" lemma="and">and</word>
  <word wid="26" pos="NNS" lemma="archive">Archives</word>
  <word wid="27" pos="NNS" lemma="recording">Recordings</word>
  <word wid="28" pos="IN" lemma="at">at</word>
  <word wid="29" pos="NN" lemma="risk">Risk</word>
  <word wid="30" pos="NNP" lemma="Mellon">Mellon</word>
  <word wid="31" pos="NNS" lemma="fellowship">Fellowships</word>
  <word wid="32" pos="IN" lemma="for">for</word>
  <word wid="33" pos="NN" lemma="dissertation">Dissertation</word>
  <word wid="34" pos="NN" lemma="research">Research</word>
  <word wid="35" pos="VBG" lemma="lead">Leading</word>
  <word wid="36" pos="NN" lemma="change">Change</word>
  <word wid="37" pos="NN" lemma="institute">Institute</word>
  <word wid="38" pos="NN" lemma="dlf">DLF</word>
  <word wid="39" pos="JJ" lemma="eresearch">eResearch</word>
  <word wid="40" pos="NN" lemma="network">Network</word>
  <word wid="41" pos="JJ" lemma="postdoctoral">Postdoctoral</word>
  <word wid="42" pos="NNP" lemma="Fellowship">Fellowship</word>
  <word wid="43" pos="NN" lemma="program">Program</word>
  <word wid="44" pos="NN" lemma="image">image</word>
  <word wid="45" pos="JJ" lemma="clir">CLIR</word>
  <word wid="46" pos="NN" lemma="image">image</word>
  <word wid="47" pos="NN" lemma="clir">CLIR</word>
  <word wid="48" pos="NN" lemma="clir">CLIR</word>
  <word wid="49" pos="NN" lemma="toggle">Toggle</word>
  <word wid="50" pos="NN" lemma="navigation">navigation</word>
  <word wid="51" pos="IN" lemma="about">About</word>
  <word wid="52" pos="NN" lemma="president">President</word>
  <word wid="53" pos="NNS" lemma="s">s</word>
  <word wid="54" pos="NN" lemma="message">Message</word>
  <word wid="55" pos="NN" lemma="news">News</word>
  <word wid="56" pos="NN" lemma="staff">Staff</word>
  <word wid="57" pos="NN" lemma="governance">Governance</word>
  <word wid="58" pos="VBP" lemma="become">Become</word>
  <word wid="59" pos="DT" lemma="a">a</word>
  <word wid="60" pos="JJ" lemma="clir">CLIR</word>
  <word wid="61" pos="NN" lemma="sponsor">Sponsor</word>
  <word wid="62" pos="CC" lemma="or">or</word>
  <word wid="63" pos="NN" lemma="dlf">DLF</word>
  <word wid="64" pos="NN" lemma="member">Member</word>
  <word wid="65" pos="JJ" lemma="current">Current</word>
  <word wid="66" pos="NNS" lemma="sponsor">Sponsors</word>
  <word wid="67" pos="NNS" lemma="member">Members</word>
  <word wid="68" pos="CC" lemma="and">and</word>
  <word wid="69" pos="NNS" lemma="funder">Funders</word>
  <word wid="70" pos="NN" lemma="history">History</word>
  <word wid="71" pos="NN" lemma="clir">CLIR</word>
  <word wid="72" pos="NN" lemma="brandmark">Brandmark</word>
  <word wid="73" pos="NNS" lemma="publication">Publications</word>
  <word wid="74" pos="VBZ" lemma="report">Reports</word>
  <word wid="75" pos="NN" lemma="clir">CLIR</word>
  <word wid="76" pos="NNS" lemma="issue">Issues</word>
  <word wid="77" pos="JJ" lemma="annual">Annual</word>
  <word wid="78" pos="NN" lemma="report">Report</word>
  <word wid="79" pos="JJ" lemma="other">Other</word>
  <word wid="80" pos="NNS" lemma="resource">Resources</word>
  <word wid="81" pos="NNS" lemma="archive">Archives</word>
  <word wid="82" pos="VBG" lemma="order">Ordering</word>
  <word wid="83" pos="CC" lemma="and">and</word>
  <word wid="84" pos="NN" lemma="customer">Customer</word>
  <word wid="85" pos="NN" lemma="service">Service</word>
  <word wid="86" pos="NNS" lemma="initiative">Initiatives</word>
  <word wid="87" pos="NN" lemma="amp">amp</word>
  <word wid="88" pos="NNS" lemma="partnership">Partnerships</word>
  <word wid="89" pos="JJ" lemma="digital">Digital</word>
  <word wid="90" pos="NN" lemma="library">Library</word>
  <word wid="91" pos="NN" lemma="federation">Federation</word>
  <word wid="92" pos="NN" lemma="chief">Chief</word>
  <word wid="93" pos="NN" lemma="information">Information</word>
  <word wid="94" pos="NNS" lemma="officer">Officers</word>
  <word wid="95" pos="IN" lemma="in">in</word>
  <word wid="96" pos="JJ" lemma="liberal">Liberal</word>
  <word wid="97" pos="NNS" lemma="art">Arts</word>
  <word wid="98" pos="NNS" lemma="college">Colleges</word>
  <word wid="99" pos="VBP" lemma="clir">CLIR</word>
  <word wid="100" pos="NNS" lemma="affiliate">Affiliates</word>
  <word wid="101" pos="JJ" lemma="digital">Digital</word>
  <word wid="102" pos="NN" lemma="library">Library</word>
  <word wid="103" pos="IN" lemma="of">of</word>
  <word wid="104" pos="DT" lemma="the">the</word>
  <word wid="105" pos="NNP" lemma="Middle">Middle</word>
  <word wid="106" pos="NNP" lemma="East">East</word>
  <word wid="107" pos="VBG" lemma="lead">Leading</word>
  <word wid="108" pos="NN" lemma="change">Change</word>
  <word wid="109" pos="NNP" lemma="Institute">Institute</word>
  <word wid="110" pos="NNP" lemma="National">National</word>
  <word wid="111" pos="NNP" lemma="Digital">Digital</word>
  <word wid="112" pos="NN" lemma="stewardship">Stewardship</word>
  <word wid="113" pos="NN" lemma="residency">Residency</word>
  <word wid="114" pos="NN" lemma="ndsr">NDSR</word>
  <word wid="115" pos="NN" lemma="assessment">Assessment</word>
  <word wid="116" pos="NNS" lemma="fellowship">Fellowships</word>
  <word wid="117" pos="NN" lemma="amp">amp</word>
  <word wid="118" pos="NNS" lemma="grant">Grants</word>
  <word wid="119" pos="VBG" lemma="digitize">Digitizing</word>
  <word wid="120" pos="JJ" lemma="hidden">Hidden</word>
  <word wid="121" pos="NNS" lemma="collection">Collections</word>
  <word wid="122" pos="NNP" lemma="Mellon">Mellon</word>
  <word wid="123" pos="NNS" lemma="fellowship">Fellowships</word>
  <word wid="124" pos="IN" lemma="for">for</word>
  <word wid="125" pos="NN" lemma="dissertation">Dissertation</word>
  <word wid="126" pos="NN" lemma="research">Research</word>
  <word wid="127" pos="IN" lemma="in">in</word>
  <word wid="128" pos="JJ" lemma="original">Original</word>
  <word wid="129" pos="NNS" lemma="source">Sources</word>
  <word wid="130" pos="JJ" lemma="postdoctoral">Postdoctoral</word>
  <word wid="131" pos="NNP" lemma="Fellowship">Fellowship</word>
  <word wid="132" pos="NN" lemma="program">Program</word>
  <word wid="133" pos="NNS" lemma="recording">Recordings</word>
  <word wid="134" pos="IN" lemma="at">at</word>
  <word wid="135" pos="NN" lemma="risk">Risk</word>
  <word wid="136" pos="NN" lemma="rovelstad">Rovelstad</word>
  <word wid="137" pos="NN" lemma="scholarship">Scholarship</word>
  <word wid="138" pos="IN" lemma="in">in</word>
  <word wid="139" pos="JJ" lemma="international">International</word>
  <word wid="140" pos="NN" lemma="librarianship">Librarianship</word>
  <word wid="141" pos="VB" lemma="connect">Connect</word>
  <word wid="142" pos="NNS" lemma="community">Communities</word>
  <word wid="143" pos="NNP" lemma="Directory">Directory</word>
  <word wid="144" pos="NNP" lemma="Re">Re</word>
  <word wid="145" pos="VBG" lemma="think">Thinking</word>
  <word wid="146" pos="NN" lemma="blog">Blog</word>
  <word wid="147" pos="NN" lemma="job">Job</word>
  <word wid="148" pos="VB" lemma="connect">Connect</word>
  <word wid="149" pos="NN" lemma="image">image</word>
  <word wid="150" pos="JJ" lemma="clir">CLIR</word>
  <word wid="151" pos="NN" lemma="image">image</word>
  <word wid="152" pos="NN" lemma="clir">CLIR</word>
  <word wid="153" pos="NN" lemma="clir">CLIR</word>
  <word wid="154" pos="NN" lemma="toggle">Toggle</word>
  <word wid="155" pos="NN" lemma="navigation">navigation</word>
  <word wid="156" pos="IN" lemma="about">About</word>
  <word wid="157" pos="NN" lemma="president">President</word>
  <word wid="158" pos="NNS" lemma="s">s</word>
  <word wid="159" pos="NN" lemma="message">Message</word>
  <word wid="160" pos="NN" lemma="news">News</word>
  <word wid="161" pos="NN" lemma="staff">Staff</word>
  <word wid="162" pos="NN" lemma="governance">Governance</word>
  <word wid="163" pos="VBP" lemma="become">Become</word>
  <word wid="164" pos="DT" lemma="a">a</word>
  <word wid="165" pos="JJ" lemma="clir">CLIR</word>
  <word wid="166" pos="NN" lemma="sponsor">Sponsor</word>
  <word wid="167" pos="CC" lemma="or">or</word>
  <word wid="168" pos="NN" lemma="dlf">DLF</word>
  <word wid="169" pos="NN" lemma="member">Member</word>
  <word wid="170" pos="JJ" lemma="current">Current</word>
  <word wid="171" pos="NNS" lemma="sponsor">Sponsors</word>
  <word wid="172" pos="NNS" lemma="member">Members</word>
  <word wid="173" pos="CC" lemma="and">and</word>
  <word wid="174" pos="NNS" lemma="funder">Funders</word>
  <word wid="175" pos="NN" lemma="history">History</word>
  <word wid="176" pos="NN" lemma="clir">CLIR</word>
  <word wid="177" pos="NN" lemma="brandmark">Brandmark</word>
  <word wid="178" pos="NNS" lemma="publication">Publications</word>
  <word wid="179" pos="VBZ" lemma="report">Reports</word>
  <word wid="180" pos="NN" lemma="clir">CLIR</word>
  <word wid="181" pos="NNS" lemma="issue">Issues</word>
  <word wid="182" pos="JJ" lemma="annual">Annual</word>
  <word wid="183" pos="NN" lemma="report">Report</word>
  <word wid="184" pos="JJ" lemma="other">Other</word>
  <word wid="185" pos="NNS" lemma="resource">Resources</word>
  <word wid="186" pos="NNS" lemma="archive">Archives</word>
  <word wid="187" pos="VBG" lemma="order">Ordering</word>
  <word wid="188" pos="CC" lemma="and">and</word>
  <word wid="189" pos="NN" lemma="customer">Customer</word>
  <word wid="190" pos="NN" lemma="service">Service</word>
  <word wid="191" pos="NNS" lemma="initiative">Initiatives</word>
  <word wid="192" pos="NN" lemma="amp">amp</word>
  <word wid="193" pos="NNS" lemma="partnership">Partnerships</word>
  <word wid="194" pos="JJ" lemma="digital">Digital</word>
  <word wid="195" pos="NN" lemma="library">Library</word>
  <word wid="196" pos="NN" lemma="federation">Federation</word>
  <word wid="197" pos="NN" lemma="chief">Chief</word>
  <word wid="198" pos="NN" lemma="information">Information</word>
  <word wid="199" pos="NNS" lemma="officer">Officers</word>
  <word wid="200" pos="IN" lemma="in">in</word>
  <word wid="201" pos="JJ" lemma="liberal">Liberal</word>
  <word wid="202" pos="NNS" lemma="art">Arts</word>
  <word wid="203" pos="NNS" lemma="college">Colleges</word>
  <word wid="204" pos="VBP" lemma="clir">CLIR</word>
  <word wid="205" pos="NNS" lemma="affiliate">Affiliates</word>
  <word wid="206" pos="JJ" lemma="digital">Digital</word>
  <word wid="207" pos="NN" lemma="library">Library</word>
  <word wid="208" pos="IN" lemma="of">of</word>
  <word wid="209" pos="DT" lemma="the">the</word>
  <word wid="210" pos="NNP" lemma="Middle">Middle</word>
  <word wid="211" pos="NNP" lemma="East">East</word>
  <word wid="212" pos="VBG" lemma="lead">Leading</word>
  <word wid="213" pos="NN" lemma="change">Change</word>
  <word wid="214" pos="NNP" lemma="Institute">Institute</word>
  <word wid="215" pos="NNP" lemma="National">National</word>
  <word wid="216" pos="NNP" lemma="Digital">Digital</word>
  <word wid="217" pos="NN" lemma="stewardship">Stewardship</word>
  <word wid="218" pos="NN" lemma="residency">Residency</word>
  <word wid="219" pos="NN" lemma="ndsr">NDSR</word>
  <word wid="220" pos="NN" lemma="assessment">Assessment</word>
  <word wid="221" pos="NNS" lemma="fellowship">Fellowships</word>
  <word wid="222" pos="NN" lemma="amp">amp</word>
  <word wid="223" pos="NNS" lemma="grant">Grants</word>
  <word wid="224" pos="VBG" lemma="digitize">Digitizing</word>
  <word wid="225" pos="JJ" lemma="hidden">Hidden</word>
  <word wid="226" pos="NNS" lemma="collection">Collections</word>
  <word wid="227" pos="NNP" lemma="Mellon">Mellon</word>
  <word wid="228" pos="NNS" lemma="fellowship">Fellowships</word>
  <word wid="229" pos="IN" lemma="for">for</word>
  <word wid="230" pos="NN" lemma="dissertation">Dissertation</word>
  <word wid="231" pos="NN" lemma="research">Research</word>
  <word wid="232" pos="IN" lemma="in">in</word>
  <word wid="233" pos="JJ" lemma="original">Original</word>
  <word wid="234" pos="NNS" lemma="source">Sources</word>
  <word wid="235" pos="JJ" lemma="postdoctoral">Postdoctoral</word>
  <word wid="236" pos="NNP" lemma="Fellowship">Fellowship</word>
  <word wid="237" pos="NN" lemma="program">Program</word>
  <word wid="238" pos="NNS" lemma="recording">Recordings</word>
  <word wid="239" pos="IN" lemma="at">at</word>
  <word wid="240" pos="NN" lemma="risk">Risk</word>
  <word wid="241" pos="NN" lemma="rovelstad">Rovelstad</word>
  <word wid="242" pos="NN" lemma="scholarship">Scholarship</word>
  <word wid="243" pos="IN" lemma="in">in</word>
  <word wid="244" pos="JJ" lemma="international">International</word>
  <word wid="245" pos="NN" lemma="librarianship">Librarianship</word>
  <word wid="246" pos="VB" lemma="connect">Connect</word>
  <word wid="247" pos="NNS" lemma="community">Communities</word>
  <word wid="248" pos="NNP" lemma="Directory">Directory</word>
  <word wid="249" pos="NNP" lemma="Re">Re</word>
  <word wid="250" pos="VBG" lemma="think">Thinking</word>
  <word wid="251" pos="NN" lemma="blog">Blog</word>
  <word wid="252" pos="NN" lemma="job">Job</word>
  <word wid="253" pos="VB" lemma="connect">Connect</word>
  <word wid="254" pos="CD" lemma="one">One</word>
  <word wid="255" pos="NN" lemma="culture">Culture</word>
  <word wid="256" pos="RB" lemma="computationally">Computationally</word>
  <word wid="257" pos="JJ" lemma="intensive">Intensive</word>
  <word wid="258" pos="NN" lemma="research">Research</word>
  <word wid="259" pos="IN" lemma="in">in</word>
  <word wid="260" pos="DT" lemma="the">the</word>
  <word wid="261" pos="NNS" lemma="humanities">Humanities</word>
  <word wid="262" pos="CC" lemma="and">and</word>
  <word wid="263" pos="NNP" lemma="Social">Social</word>
  <word wid="264" pos="NNP" lemma="Sciences">Sciences</word>
  <word wid="265" pos="NNP" lemma="Home">Home</word>
  <word wid="266" pos="NNP" lemma="CLIR">CLIR</word>
  <word wid="267" pos="NNP" lemma="Publications">Publications</word>
  <word wid="268" pos="NNP" lemma="CLIR">CLIR</word>
  <word wid="269" pos="VBZ" lemma="report">Reports</word>
  <word wid="270" pos="CD" lemma="one">One</word>
  <word wid="271" pos="NN" lemma="culture">Culture</word>
  <word wid="272" pos="NN" lemma="computa">Computa</word>
  <word wid="273" pos="NN" lemma="image">image</word>
  <word wid="274" pos="CD" lemma="one">One</word>
  <word wid="275" pos="NN" lemma="culture">Culture</word>
  <word wid="276" pos="RB" lemma="computationally">Computationally</word>
  <word wid="277" pos="JJ" lemma="intensive">Intensive</word>
  <word wid="278" pos="NN" lemma="research">Research</word>
  <word wid="279" pos="IN" lemma="in">in</word>
  <word wid="280" pos="DT" lemma="the">the</word>
  <word wid="281" pos="NNS" lemma="humanities">Humanities</word>
  <word wid="282" pos="CC" lemma="and">and</word>
  <word wid="283" pos="NNP" lemma="Social">Social</word>
  <word wid="284" pos="NNPS" lemma="Sciences">Sciences</word>
  <word wid="285" pos="DT" lemma="a">A</word>
  <word wid="286" pos="NN" lemma="report">Report</word>
  <word wid="287" pos="IN" lemma="on">on</word>
  <word wid="288" pos="DT" lemma="the">the</word>
  <word wid="289" pos="NNS" lemma="experience">Experiences</word>
  <word wid="290" pos="IN" lemma="of">of</word>
  <word wid="291" pos="JJ" lemma="first">First</word>
  <word wid="292" pos="NNS" lemma="respondent">Respondents</word>
  <word wid="293" pos="TO" lemma="to">to</word>
  <word wid="294" pos="DT" lemma="the">the</word>
  <word wid="295" pos="NN" lemma="digging">Digging</word>
  <word wid="296" pos="IN" lemma="into">Into</word>
  <word wid="297" pos="NNS" lemma="datum">Data</word>
  <word wid="298" pos="NN" lemma="challenge">Challenge</word>
  <word wid="299" pos="IN" lemma="by">by</word>
  <word wid="300" pos="NNP" lemma="Christa">Christa</word>
  <word wid="301" pos="NNP" lemma="Williford">Williford</word>
  <word wid="302" pos="CC" lemma="and">and</word>
  <word wid="303" pos="NNP" lemma="Charles">Charles</word>
  <word wid="304" pos="NNP" lemma="Henry">Henry</word>
  <word wid="305" pos="NNP" lemma="Research">Research</word>
  <word wid="306" pos="NN" lemma="design">Design</word>
  <word wid="307" pos="IN" lemma="by">by</word>
  <word wid="308" pos="NNP" lemma="Amy">Amy</word>
  <word wid="309" pos="NNP" lemma="Friedlander">Friedlander</word>
  <word wid="310" pos="NNP" lemma="June">June</word>
  <word wid="311" pos="CD" lemma="2012">2012</word>
  <word wid="312" pos="CD" lemma="44">44</word>
  <word wid="313" pos="NN" lemma="pp">pp</word>
  <word wid="314" pos="CD" lemma="20">20</word>
  <word wid="315" pos="NN" lemma="isbn">ISBN</word>
  <word wid="316" pos="CD" lemma="978">978</word>
  <word wid="317" pos="CD" lemma="1">1</word>
  <word wid="318" pos="CD" lemma="932326">932326</word>
  <word wid="319" pos="CD" lemma="40">40</word>
  <word wid="320" pos="CD" lemma="6">6</word>
  <word wid="321" pos="NN" lemma="clir">CLIR</word>
  <word wid="322" pos="NN" lemma="pub151">pub151</word>
  <word wid="323" pos="NN" lemma="pdf">PDF</word>
  <word wid="324" pos="NN" lemma="download">Download</word>
  <word wid="325" pos="IN" lemma="of">of</word>
  <word wid="326" pos="JJ" lemma="main">Main</word>
  <word wid="327" pos="NN" lemma="report">Report</word>
  <word wid="328" pos="VBG" lemma="exclude">excluding</word>
  <word wid="329" pos="NN" lemma="case">case</word>
  <word wid="330" pos="NNS" lemma="study">studies</word>
  <word wid="331" pos="CD" lemma="1">1</word>
  <word wid="332" pos="NN" lemma="mb">MB</word>
  <word wid="333" pos="NN" lemma="file">file</word>
  <word wid="334" pos="NN" lemma="gt">gt</word>
  <word wid="335" pos="NN" lemma="gt">gt</word>
  <word wid="336" pos="JJ" lemma="full">Full</word>
  <word wid="337" pos="NN" lemma="text">Text</word>
  <word wid="338" pos="IN" lemma="of">of</word>
  <word wid="339" pos="JJ" lemma="main">Main</word>
  <word wid="340" pos="NN" lemma="report">Report</word>
  <word wid="341" pos="NN" lemma="gt">gt</word>
  <word wid="342" pos="NN" lemma="gt">gt</word>
  <word wid="343" pos="DT" lemma="this">This</word>
  <word wid="344" pos="NN" lemma="report">report</word>
  <word wid="345" pos="VBZ" lemma="culminate">culminates</word>
  <word wid="346" pos="CD" lemma="two">two</word>
  <word wid="347" pos="NNS" lemma="year">years</word>
  <word wid="348" pos="IN" lemma="of">of</word>
  <word wid="349" pos="NN" lemma="work">work</word>
  <word wid="350" pos="IN" lemma="by">by</word>
  <word wid="351" pos="JJ" lemma="clir">CLIR</word>
  <word wid="352" pos="NN" lemma="staff">staff</word>
  <word wid="353" pos="VBG" lemma="involve">involving</word>
  <word wid="354" pos="JJ" lemma="extensive">extensive</word>
  <word wid="355" pos="NNS" lemma="interview">interviews</word>
  <word wid="356" pos="CC" lemma="and">and</word>
  <word wid="357" pos="NN" lemma="site">site</word>
  <word wid="358" pos="NNS" lemma="visit">visits</word>
  <word wid="359" pos="IN" lemma="with">with</word>
  <word wid="360" pos="NNS" lemma="scholar">scholars</word>
  <word wid="361" pos="VBN" lemma="engage">engaged</word>
  <word wid="362" pos="IN" lemma="in">in</word>
  <word wid="363" pos="JJ" lemma="international">international</word>
  <word wid="364" pos="NN" lemma="research">research</word>
  <word wid="365" pos="NNS" lemma="collaboration">collaborations</word>
  <word wid="366" pos="VBG" lemma="involve">involving</word>
  <word wid="367" pos="JJ" lemma="computational">computational</word>
  <word wid="368" pos="NN" lemma="analysis">analysis</word>
  <word wid="369" pos="IN" lemma="of">of</word>
  <word wid="370" pos="JJ" lemma="large">large</word>
  <word wid="371" pos="NNS" lemma="datum">data</word>
  <word wid="372" pos="NN" lemma="corpora">corpora</word>
  <word wid="373" pos="DT" lemma="these">These</word>
  <word wid="374" pos="NNS" lemma="scholar">scholars</word>
  <word wid="375" pos="VBD" lemma="be">were</word>
  <word wid="376" pos="DT" lemma="the">the</word>
  <word wid="377" pos="JJ" lemma="first">first</word>
  <word wid="378" pos="NNS" lemma="recipient">recipients</word>
  <word wid="379" pos="IN" lemma="of">of</word>
  <word wid="380" pos="NNS" lemma="grant">grants</word>
  <word wid="381" pos="IN" lemma="through">through</word>
  <word wid="382" pos="DT" lemma="the">the</word>
  <word wid="383" pos="NN" lemma="digging">Digging</word>
  <word wid="384" pos="IN" lemma="into">into</word>
  <word wid="385" pos="NNS" lemma="datum">Data</word>
  <word wid="386" pos="NN" lemma="program">program</word>
  <word wid="387" pos="VBN" lemma="lead">led</word>
  <word wid="388" pos="IN" lemma="by">by</word>
  <word wid="389" pos="DT" lemma="the">the</word>
  <word wid="390" pos="NN" lemma="neh">NEH</word>
  <word wid="391" pos="WP" lemma="who">who</word>
  <word wid="392" pos="VBD" lemma="partner">partnered</word>
  <word wid="393" pos="IN" lemma="with">with</word>
  <word wid="394" pos="NN" lemma="jisc">JISC</word>
  <word wid="395" pos="IN" lemma="in">in</word>
  <word wid="396" pos="DT" lemma="the">the</word>
  <word wid="397" pos="NNP" lemma="UK">UK</word>
  <word wid="398" pos="NNP" lemma="SSHRC">SSHRC</word>
  <word wid="399" pos="IN" lemma="in">in</word>
  <word wid="400" pos="NNP" lemma="Canada">Canada</word>
  <word wid="401" pos="CC" lemma="and">and</word>
  <word wid="402" pos="DT" lemma="the">the</word>
  <word wid="403" pos="NN" lemma="nsf">NSF</word>
  <word wid="404" pos="TO" lemma="to">to</word>
  <word wid="405" pos="VB" lemma="fund">fund</word>
  <word wid="406" pos="DT" lemma="the">the</word>
  <word wid="407" pos="JJ" lemma="first">first</word>
  <word wid="408" pos="CD" lemma="eight">eight</word>
  <word wid="409" pos="NNS" lemma="initiative">initiatives</word>
  <word wid="410" pos="DT" lemma="the">The</word>
  <word wid="411" pos="NN" lemma="report">report</word>
  <word wid="412" pos="VBZ" lemma="introduce">introduces</word>
  <word wid="413" pos="DT" lemma="the">the</word>
  <word wid="414" pos="CD" lemma="eight">eight</word>
  <word wid="415" pos="NNS" lemma="project">projects</word>
  <word wid="416" pos="CC" lemma="and">and</word>
  <word wid="417" pos="VBZ" lemma="discuss">discusses</word>
  <word wid="418" pos="DT" lemma="the">the</word>
  <word wid="419" pos="NN" lemma="importance">importance</word>
  <word wid="420" pos="IN" lemma="of">of</word>
  <word wid="421" pos="DT" lemma="these">these</word>
  <word wid="422" pos="NNS" lemma="case">cases</word>
  <word wid="423" pos="IN" lemma="as">as</word>
  <word wid="424" pos="NNS" lemma="model">models</word>
  <word wid="425" pos="IN" lemma="for">for</word>
  <word wid="426" pos="DT" lemma="the">the</word>
  <word wid="427" pos="NN" lemma="future">future</word>
  <word wid="428" pos="IN" lemma="of">of</word>
  <word wid="429" pos="NN" lemma="research">research</word>
  <word wid="430" pos="IN" lemma="in">in</word>
  <word wid="431" pos="DT" lemma="the">the</word>
  <word wid="432" pos="NNP" lemma="academy">academy</word>
  <word wid="433" pos="JJ" lemma="additional">Additional</word>
  <word wid="434" pos="NN" lemma="information">information</word>
  <word wid="435" pos="IN" lemma="about">about</word>
  <word wid="436" pos="DT" lemma="the">the</word>
  <word wid="437" pos="NNS" lemma="project">projects</word>
  <word wid="438" pos="VBZ" lemma="be">is</word>
  <word wid="439" pos="VBN" lemma="provide">provided</word>
  <word wid="440" pos="IN" lemma="in">in</word>
  <word wid="441" pos="DT" lemma="the">the</word>
  <word wid="442" pos="JJ" lemma="individual">individual</word>
  <word wid="443" pos="NN" lemma="case">case</word>
  <word wid="444" pos="NNS" lemma="study">studies</word>
  <word wid="445" pos="IN" lemma="below">below</word>
  <word wid="446" pos="DT" lemma="this">this</word>
  <word wid="447" pos="JJ" lemma="additional">additional</word>
  <word wid="448" pos="NN" lemma="material">material</word>
  <word wid="449" pos="VBZ" lemma="be">is</word>
  <word wid="450" pos="RB" lemma="not">not</word>
  <word wid="451" pos="VBN" lemma="include">included</word>
  <word wid="452" pos="IN" lemma="in">in</word>
  <word wid="453" pos="DT" lemma="the">the</word>
  <word wid="454" pos="NN" lemma="print">print</word>
  <word wid="455" pos="CC" lemma="or">or</word>
  <word wid="456" pos="NN" lemma="pdf">PDF</word>
  <word wid="457" pos="NNS" lemma="version">versions</word>
  <word wid="458" pos="IN" lemma="of">of</word>
  <word wid="459" pos="DT" lemma="the">the</word>
  <word wid="460" pos="VBN" lemma="publish">published</word>
  <word wid="461" pos="NN" lemma="report">report</word>
  <word wid="462" pos="NN" lemma="report">Report</word>
  <word wid="463" pos="NNS" lemma="recommendation">Recommendations</word>
  <word wid="464" pos="CD" lemma="1">1</word>
  <word wid="465" pos="VB" lemma="expand">Expand</word>
  <word wid="466" pos="PRP$" lemma="we">our</word>
  <word wid="467" pos="NN" lemma="concept">concept</word>
  <word wid="468" pos="IN" lemma="of">of</word>
  <word wid="469" pos="NN" lemma="research">research</word>
  <word wid="470" pos="CD" lemma="2">2</word>
  <word wid="471" pos="VB" lemma="expand">Expand</word>
  <word wid="472" pos="PRP$" lemma="we">our</word>
  <word wid="473" pos="NN" lemma="concept">concept</word>
  <word wid="474" pos="IN" lemma="of">of</word>
  <word wid="475" pos="NN" lemma="research">research</word>
  <word wid="476" pos="NNS" lemma="datum">data</word>
  <word wid="477" pos="CC" lemma="and">and</word>
  <word wid="478" pos="VB" lemma="accept">accept</word>
  <word wid="479" pos="DT" lemma="the">the</word>
  <word wid="480" pos="NNS" lemma="challenge">challenges</word>
  <word wid="481" pos="IN" lemma="that">that</word>
  <word wid="482" pos="NNP" lemma="digital">digital</word>
  <word wid="483" pos="NNP" lemma="research">research</word>
  <word wid="484" pos="NNP" lemma="data">data</word>
  <word wid="485" pos="JJ" lemma="present">present</word>
  <word wid="486" pos="CD" lemma="3">3</word>
  <word wid="487" pos="VBP" lemma="embrace">Embrace</word>
  <word wid="488" pos="NN" lemma="interdisciplinarity">interdisciplinarity</word>
  <word wid="489" pos="CD" lemma="4">4</word>
  <word wid="490" pos="VBP" lemma="take">Take</word>
  <word wid="491" pos="DT" lemma="a">a</word>
  <word wid="492" pos="JJR" lemma="more">more</word>
  <word wid="493" pos="JJ" lemma="inclusive">inclusive</word>
  <word wid="494" pos="NN" lemma="approach">approach</word>
  <word wid="495" pos="TO" lemma="to">to</word>
  <word wid="496" pos="NN" lemma="collaboration">collaboration</word>
  <word wid="497" pos="CD" lemma="5">5</word>
  <word wid="498" pos="NN" lemma="address">Address</word>
  <word wid="499" pos="NNS" lemma="gap">gaps</word>
  <word wid="500" pos="IN" lemma="in">in</word>
  <word wid="501" pos="NN" lemma="training">training</word>
  <word wid="502" pos="CD" lemma="6">6</word>
  <word wid="503" pos="VB" lemma="adopt">Adopt</word>
  <word wid="504" pos="NNS" lemma="model">models</word>
  <word wid="505" pos="IN" lemma="for">for</word>
  <word wid="506" pos="VBG" lemma="share">sharing</word>
  <word wid="507" pos="NN" lemma="credit">credit</word>
  <word wid="508" pos="CD" lemma="7">7</word>
  <word wid="509" pos="VB" lemma="adopt">Adopt</word>
  <word wid="510" pos="NNS" lemma="model">models</word>
  <word wid="511" pos="IN" lemma="for">for</word>
  <word wid="512" pos="VBG" lemma="share">sharing</word>
  <word wid="513" pos="NNS" lemma="resource">resources</word>
  <word wid="514" pos="CD" lemma="8">8</word>
  <word wid="515" pos="NNP" lemma="Re">Re</word>
  <word wid="516" pos="VB" lemma="envision">envision</word>
  <word wid="517" pos="JJ" lemma="scholarly">scholarly</word>
  <word wid="518" pos="NN" lemma="publication">publication</word>
  <word wid="519" pos="CD" lemma="9">9</word>
  <word wid="520" pos="VBP" lemma="make">Make</word>
  <word wid="521" pos="JJR" lemma="greater">greater</word>
  <word wid="522" pos="JJ" lemma="sustained">sustained</word>
  <word wid="523" pos="NNS" lemma="investment">investments</word>
  <word wid="524" pos="IN" lemma="in">in</word>
  <word wid="525" pos="JJ" lemma="human">human</word>
  <word wid="526" pos="CC" lemma="and">and</word>
  <word wid="527" pos="NN" lemma="cyberinfrastructure">cyberinfrastructure</word>
  <word wid="528" pos="NN" lemma="case">Case</word>
  <word wid="529" pos="NNS" lemma="study">Studies</word>
  <word wid="530" pos="NN" lemma="introduction">Introduction</word>
  <word wid="531" pos="VBG" lemma="use">Using</word>
  <word wid="532" pos="NN" lemma="zotero">Zotero</word>
  <word wid="533" pos="CC" lemma="and">and</word>
  <word wid="534" pos="NN" lemma="tapor">TAPOR</word>
  <word wid="535" pos="IN" lemma="on">on</word>
  <word wid="536" pos="DT" lemma="the">the</word>
  <word wid="537" pos="JJ" lemma="old">Old</word>
  <word wid="538" pos="NNP" lemma="Bailey">Bailey</word>
  <word wid="539" pos="NNP" lemma="Proceedings">Proceedings</word>
  <word wid="540" pos="NNP" lemma="Data">Data</word>
  <word wid="541" pos="NN" lemma="mining">Mining</word>
  <word wid="542" pos="IN" lemma="with">with</word>
  <word wid="543" pos="JJ" lemma="criminal">Criminal</word>
  <word wid="544" pos="NN" lemma="intent">Intent</word>
  <word wid="545" pos="NN" lemma="dmci">DMCI</word>
  <word wid="546" pos="NN" lemma="digging">Digging</word>
  <word wid="547" pos="IN" lemma="into">into</word>
  <word wid="548" pos="DT" lemma="the">the</word>
  <word wid="549" pos="NN" lemma="enlightenment">Enlightenment</word>
  <word wid="550" pos="VBG" lemma="map">Mapping</word>
  <word wid="551" pos="DT" lemma="the">the</word>
  <word wid="552" pos="NN" lemma="republic">Republic</word>
  <word wid="553" pos="IN" lemma="of">of</word>
  <word wid="554" pos="NNS" lemma="letter">Letters</word>
  <word wid="555" pos="IN" lemma="towards">Towards</word>
  <word wid="556" pos="JJ" lemma="dynamic">Dynamic</word>
  <word wid="557" pos="NN" lemma="variorum">Variorum</word>
  <word wid="558" pos="NNS" lemma="edition">Editions</word>
  <word wid="559" pos="VBP" lemma="dve">DVE</word>
  <word wid="560" pos="VBG" lemma="mine">Mining</word>
  <word wid="561" pos="DT" lemma="a">a</word>
  <word wid="562" pos="NN" lemma="year">Year</word>
  <word wid="563" pos="IN" lemma="of">of</word>
  <word wid="564" pos="NN" lemma="speech">Speech</word>
  <word wid="565" pos="VBG" lemma="harvest">Harvesting</word>
  <word wid="566" pos="NN" lemma="speech">Speech</word>
  <word wid="567" pos="NNS" lemma="dataset">Datasets</word>
  <word wid="568" pos="IN" lemma="for">for</word>
  <word wid="569" pos="JJ" lemma="linguistic">Linguistic</word>
  <word wid="570" pos="NN" lemma="research">Research</word>
  <word wid="571" pos="IN" lemma="on">on</word>
  <word wid="572" pos="DT" lemma="the">the</word>
  <word wid="573" pos="NN" lemma="web">Web</word>
  <word wid="574" pos="JJ" lemma="structural">Structural</word>
  <word wid="575" pos="NN" lemma="analysis">Analysis</word>
  <word wid="576" pos="IN" lemma="of">of</word>
  <word wid="577" pos="JJ" lemma="large">Large</word>
  <word wid="578" pos="NNS" lemma="amount">Amounts</word>
  <word wid="579" pos="IN" lemma="of">of</word>
  <word wid="580" pos="NN" lemma="music">Music</word>
  <word wid="581" pos="NN" lemma="information">Information</word>
  <word wid="582" pos="NN" lemma="salami">SALAMI</word>
  <word wid="583" pos="NN" lemma="digging">Digging</word>
  <word wid="584" pos="IN" lemma="into">into</word>
  <word wid="585" pos="NN" lemma="image">Image</word>
  <word wid="586" pos="NNS" lemma="datum">Data</word>
  <word wid="587" pos="TO" lemma="to">to</word>
  <word wid="588" pos="VB" lemma="answer">Answer</word>
  <word wid="589" pos="NN" lemma="authorship">Authorship</word>
  <word wid="590" pos="JJ" lemma="related">Related</word>
  <word wid="591" pos="NNS" lemma="question">Questions</word>
  <word wid="592" pos="VBD" lemma="do">DID</word>
  <word wid="593" pos="NN" lemma="arq">ARQ</word>
  <word wid="594" pos="NNS" lemma="railroad">Railroads</word>
  <word wid="595" pos="CC" lemma="and">and</word>
  <word wid="596" pos="DT" lemma="the">the</word>
  <word wid="597" pos="NN" lemma="making">Making</word>
  <word wid="598" pos="IN" lemma="of">of</word>
  <word wid="599" pos="JJ" lemma="modern">Modern</word>
  <word wid="600" pos="NNP" lemma="America">America</word>
  <word wid="601" pos="NNP" lemma="CLIR">CLIR</word>
  <word wid="602" pos="VBZ" lemma="wish">wishes</word>
  <word wid="603" pos="TO" lemma="to">to</word>
  <word wid="604" pos="VB" lemma="acknowledge">acknowledge</word>
  <word wid="605" pos="DT" lemma="the">the</word>
  <word wid="606" pos="NN" lemma="support">support</word>
  <word wid="607" pos="CC" lemma="and">and</word>
  <word wid="608" pos="NN" lemma="assistance">assistance</word>
  <word wid="609" pos="IN" lemma="of">of</word>
  <word wid="610" pos="DT" lemma="the">the</word>
  <word wid="611" pos="CD" lemma="four">four</word>
  <word wid="612" pos="NNS" lemma="funder">funders</word>
  <word wid="613" pos="IN" lemma="of">of</word>
  <word wid="614" pos="DT" lemma="the">the</word>
  <word wid="615" pos="CD" lemma="2009">2009</word>
  <word wid="616" pos="NN" lemma="digging">Digging</word>
  <word wid="617" pos="IN" lemma="into">into</word>
  <word wid="618" pos="NNS" lemma="datum">Data</word>
  <word wid="619" pos="VBP" lemma="challenge">Challenge</word>
  <word wid="620" pos="JJ" lemma="national">National</word>
  <word wid="621" pos="NN" lemma="endowment">Endowment</word>
  <word wid="622" pos="IN" lemma="for">for</word>
  <word wid="623" pos="DT" lemma="the">the</word>
  <word wid="624" pos="NNS" lemma="humanities">Humanities</word>
  <word wid="625" pos="NNP" lemma="JISC">JISC</word>
  <word wid="626" pos="NNP" lemma="National">National</word>
  <word wid="627" pos="NNP" lemma="Science">Science</word>
  <word wid="628" pos="NNP" lemma="Foundation">Foundation</word>
  <word wid="629" pos="NNP" lemma="Social">Social</word>
  <word wid="630" pos="NNPS" lemma="Sciences">Sciences</word>
  <word wid="631" pos="CC" lemma="and">and</word>
  <word wid="632" pos="NNS" lemma="humanities">Humanities</word>
  <word wid="633" pos="NN" lemma="research">Research</word>
  <word wid="634" pos="NN" lemma="council">Council</word>
  <word wid="635" pos="IN" lemma="of">of</word>
  <word wid="636" pos="NNP" lemma="Canada">Canada</word>
  <word wid="637" pos="RB" lemma="as">as</word>
  <word wid="638" pos="RB" lemma="well">well</word>
  <word wid="639" pos="IN" lemma="as">as</word>
  <word wid="640" pos="DT" lemma="the">the</word>
  <word wid="641" pos="NN" lemma="lead">lead</word>
  <word wid="642" pos="NN" lemma="program">program</word>
  <word wid="643" pos="NNS" lemma="officer">officers</word>
  <word wid="644" pos="IN" lemma="for">for</word>
  <word wid="645" pos="DT" lemma="the">the</word>
  <word wid="646" pos="CD" lemma="2009">2009</word>
  <word wid="647" pos="NN" lemma="grant">grant</word>
  <word wid="648" pos="NN" lemma="program">program</word>
  <word wid="649" pos="NNP" lemma="Alastair">Alastair</word>
  <word wid="650" pos="NNP" lemma="Dunning">Dunning</word>
  <word wid="651" pos="NNP" lemma="JISC">JISC</word>
  <word wid="652" pos="NNP" lemma="Mika">Mika</word>
  <word wid="653" pos="JJ" lemma="oehling">Oehling</word>
  <word wid="654" pos="NN" lemma="sshrc">SSHRC</word>
  <word wid="655" pos="NNP" lemma="Jennifer">Jennifer</word>
  <word wid="656" pos="NNP" lemma="Serventi">Serventi</word>
  <word wid="657" pos="NNP" lemma="NEH">NEH</word>
  <word wid="658" pos="CC" lemma="and">and</word>
  <word wid="659" pos="NNP" lemma="Elizabeth">Elizabeth</word>
  <word wid="660" pos="NNP" lemma="Tran">Tran</word>
  <word wid="661" pos="NNP" lemma="NSF">NSF</word>
  <word wid="662" pos="CD" lemma="one">One</word>
  <word wid="663" pos="NN" lemma="culture">Culture</word>
  <word wid="664" pos="RB" lemma="computationally">Computationally</word>
  <word wid="665" pos="JJ" lemma="intensive">Intensive</word>
  <word wid="666" pos="NN" lemma="research">Research</word>
  <word wid="667" pos="IN" lemma="in">in</word>
  <word wid="668" pos="DT" lemma="the">the</word>
  <word wid="669" pos="NNS" lemma="humanities">Humanities</word>
  <word wid="670" pos="CC" lemma="and">and</word>
  <word wid="671" pos="NNP" lemma="Social">Social</word>
  <word wid="672" pos="NNPS" lemma="Sciences">Sciences</word>
  <word wid="673" pos="DT" lemma="a">A</word>
  <word wid="674" pos="NN" lemma="report">Report</word>
  <word wid="675" pos="IN" lemma="on">on</word>
  <word wid="676" pos="DT" lemma="the">the</word>
  <word wid="677" pos="NNS" lemma="experience">Experiences</word>
  <word wid="678" pos="IN" lemma="of">of</word>
  <word wid="679" pos="JJ" lemma="first">First</word>
  <word wid="680" pos="NNS" lemma="respondent">Respondents</word>
  <word wid="681" pos="TO" lemma="to">to</word>
  <word wid="682" pos="DT" lemma="the">the</word>
  <word wid="683" pos="NN" lemma="digging">Digging</word>
  <word wid="684" pos="IN" lemma="into">into</word>
  <word wid="685" pos="NNS" lemma="datum">Data</word>
  <word wid="686" pos="NN" lemma="challenge">Challenge</word>
  <word wid="687" pos="IN" lemma="by">by</word>
  <word wid="688" pos="NNP" lemma="Christa">Christa</word>
  <word wid="689" pos="NNP" lemma="Williford">Williford</word>
  <word wid="690" pos="CC" lemma="and">and</word>
  <word wid="691" pos="NNP" lemma="Charles">Charles</word>
  <word wid="692" pos="NNP" lemma="Henry">Henry</word>
  <word wid="693" pos="NNP" lemma="Research">Research</word>
  <word wid="694" pos="NN" lemma="design">Design</word>
  <word wid="695" pos="IN" lemma="by">by</word>
  <word wid="696" pos="NNP" lemma="Amy">Amy</word>
  <word wid="697" pos="NNP" lemma="Friedlander">Friedlander</word>
  <word wid="698" pos="VBZ" lemma="be">is</word>
  <word wid="699" pos="VBN" lemma="license">licensed</word>
  <word wid="700" pos="IN" lemma="under">under</word>
  <word wid="701" pos="DT" lemma="a">a</word>
  <word wid="702" pos="JJ" lemma="creative">Creative</word>
  <word wid="703" pos="NNP" lemma="Commons">Commons</word>
  <word wid="704" pos="NN" lemma="attribution">Attribution</word>
  <word wid="705" pos="JJ" lemma="noncommercial">NonCommercial</word>
  <word wid="706" pos="JJ" lemma="sharealike">ShareAlike</word>
  <word wid="707" pos="CD" lemma="3">3</word>
  <word wid="708" pos="CD" lemma="0">0</word>
  <word wid="709" pos="JJ" lemma="unported">Unported</word>
  <word wid="710" pos="NN" lemma="license">License</word>
  <word wid="711" pos="VBN" lemma="base">Based</word>
  <word wid="712" pos="IN" lemma="on">on</word>
  <word wid="713" pos="DT" lemma="a">a</word>
  <word wid="714" pos="NN" lemma="work">work</word>
  <word wid="715" pos="IN" lemma="at">at</word>
  <word wid="716" pos="NNP" lemma="www">www</word>
  <word wid="717" pos="NNP" lemma="clir">clir</word>
  <word wid="718" pos="NNP" lemma="org">org</word>
  <word wid="719" pos="NN" lemma="order">ORDER</word>
  <word wid="720" pos="NN" lemma="print">PRINT</word>
  <word wid="721" pos="NNS" lemma="copy">COPIES</word>
  <word wid="722" pos="NN" lemma="order">Order</word>
  <word wid="723" pos="CD" lemma="one">One</word>
  <word wid="724" pos="NN" lemma="culture">Culture</word>
  <word wid="725" pos="RB" lemma="computationally">Computationally</word>
  <word wid="726" pos="JJ" lemma="intensive">Intensive</word>
  <word wid="727" pos="NN" lemma="research">Research</word>
  <word wid="728" pos="IN" lemma="in">in</word>
  <word wid="729" pos="DT" lemma="the">the</word>
  <word wid="730" pos="NNS" lemma="humanities">Humanities</word>
  <word wid="731" pos="CC" lemma="and">and</word>
  <word wid="732" pos="NNP" lemma="Social">Social</word>
  <word wid="733" pos="NNPS" lemma="Sciences">Sciences</word>
  <word wid="734" pos="RB" lemma="here">here</word>
  <word wid="735" pos="RB" lemma="simply">Simply</word>
  <word wid="736" pos="VB" lemma="indicate">indicate</word>
  <word wid="737" pos="DT" lemma="the">the</word>
  <word wid="738" pos="NN" lemma="quantity">Quantity</word>
  <word wid="739" pos="CC" lemma="and">and</word>
  <word wid="740" pos="VB" lemma="click">click</word>
  <word wid="741" pos="IN" lemma="on">on</word>
  <word wid="742" pos="PRP" lemma="we">We</word>
  <word wid="743" pos="VBP" lemma="use">use</word>
  <word wid="744" pos="DT" lemma="a">an</word>
  <word wid="745" pos="JJ" lemma="independent">independent</word>
  <word wid="746" pos="JJ" lemma="online">online</word>
  <word wid="747" pos="NN" lemma="retailer">retailer</word>
  <word wid="748" pos="TO" lemma="to">to</word>
  <word wid="749" pos="VB" lemma="take">take</word>
  <word wid="750" pos="JJ" lemma="online">online</word>
  <word wid="751" pos="NNS" lemma="order">orders</word>
  <word wid="752" pos="IN" lemma="for">for</word>
  <word wid="753" pos="PRP" lemma="we">us</word>
  <word wid="754" pos="CC" lemma="and">and</word>
  <word wid="755" pos="VB" lemma="ship">ship</word>
  <word wid="756" pos="NNS" lemma="publication">publications</word>
  <word wid="757" pos="RB" lemma="directly">directly</word>
  <word wid="758" pos="TO" lemma="to">to</word>
  <word wid="759" pos="PRP" lemma="you">you</word>
  <word wid="760" pos="VBP" lemma="find">Find</word>
  <word wid="761" pos="JJR" lemma="more">more</word>
  <word wid="762" pos="NNS" lemma="detail">details</word>
  <word wid="763" pos="IN" lemma="about">about</word>
  <word wid="764" pos="DT" lemma="the">the</word>
  <word wid="765" pos="VBG" lemma="order">ordering</word>
  <word wid="766" pos="NN" lemma="process">process</word>
  <word wid="767" pos="NN" lemma="gt">gt</word>
  <word wid="768" pos="NN" lemma="gt">gt</word>
  <word wid="769" pos="NN" lemma="contact">Contact</word>
  <word wid="770" pos="NN" lemma="clir">CLIR</word>
  <word wid="771" pos="CD" lemma="1707">1707</word>
  <word wid="772" pos="NN" lemma="l">L</word>
  <word wid="773" pos="JJ" lemma="st">St</word>
  <word wid="774" pos="NN" lemma="nw">NW</word>
  <word wid="775" pos="NN" lemma="suite">Suite</word>
  <word wid="776" pos="CD" lemma="650">650</word>
  <word wid="777" pos="NNP" lemma="Washington">Washington</word>
  <word wid="778" pos="NNP" lemma="DC">DC</word>
  <word wid="779" pos="CD" lemma="20036">20036</word>
  <word wid="780" pos="NN" lemma="p">P</word>
  <word wid="781" pos="JJ" lemma="202 939 4750">202 939 4750</word>
  <word wid="782" pos="NN" lemma="privacy">Privacy</word>
  <word wid="783" pos="NN" lemma="amp">amp</word>
  <word wid="784" pos="NNS" lemma="cookie">Cookies</word>
  <word wid="785" pos="DT" lemma="this">This</word>
  <word wid="786" pos="NN" lemma="site">site</word>
  <word wid="787" pos="VBZ" lemma="use">uses</word>
  <word wid="788" pos="NNS" lemma="cookie">cookies</word>
  <word wid="789" pos="TO" lemma="to">To</word>
  <word wid="790" pos="VB" lemma="find">find</word>
  <word wid="791" pos="RP" lemma="out">out</word>
  <word wid="792" pos="RBR" lemma="more">more</word>
  <word wid="793" pos="RB" lemma="as">as</word>
  <word wid="794" pos="RB" lemma="well">well</word>
  <word wid="795" pos="IN" lemma="as">as</word>
  <word wid="796" pos="WRB" lemma="how">how</word>
  <word wid="797" pos="TO" lemma="to">to</word>
  <word wid="798" pos="VB" lemma="remove">remove</word>
  <word wid="799" pos="CC" lemma="or">or</word>
  <word wid="800" pos="VB" lemma="block">block</word>
  <word wid="801" pos="DT" lemma="these">these</word>
  <word wid="802" pos="VBP" lemma="see">see</word>
  <word wid="803" pos="RB" lemma="here">here</word>
  <word wid="804" pos="PRP$" lemma="we">Our</word>
  <word wid="805" pos="NN" lemma="cookie">Cookie</word>
  <word wid="806" pos="NN" lemma="policy">Policy</word>
  <word wid="807" pos="RB" lemma="elsewhere">Elsewhere</word>
  <word wid="808" pos="NNP" lemma="Facebook">Facebook</word>
  <word wid="809" pos="NNP" lemma="Twitter">Twitter</word>
  <word wid="810" pos="NNP" lemma="LinkedIn">LinkedIn</word>
  <word wid="811" pos="NNP" lemma="YouTube">YouTube</word>
  <word wid="812" pos="NNP" lemma="RSS">RSS</word>
  <word wid="813" pos="VB" lemma="stay">Stay</word>
  <word wid="814" pos="IN" lemma="in">in</word>
  <word wid="815" pos="NN" lemma="touch">Touch</word>
  <word wid="816" pos="NN" lemma="email">Email</word>
  <word wid="817" pos="JJ" lemma="first">First</word>
  <word wid="818" pos="NN" lemma="name">Name</word>
  <word wid="819" pos="JJ" lemma="last">Last</word>
  <word wid="820" pos="NN" lemma="name">Name</word>
  <word wid="821" pos="JJ" lemma="sorry">Sorry</word>
  <word wid="822" pos="PRP" lemma="you">You</word>
  <word wid="823" pos="MD" lemma="must">must</word>
  <word wid="824" pos="VB" lemma="have">have</word>
  <word wid="825" pos="NNP" lemma="JavaScript">JavaScript</word>
  <word wid="826" pos="VBD" lemma="enable">enabled</word>
  <word wid="827" pos="TO" lemma="to">to</word>
  <word wid="828" pos="VB" lemma="fill">fill</word>
  <word wid="829" pos="RP" lemma="out">out</word>
  <word wid="830" pos="DT" lemma="this">this</word>
  <word wid="831" pos="NN" lemma="form">form</word>
  <word wid="832" pos="VB" lemma="please">Please</word>
  <word wid="833" pos="VB" lemma="complete">complete</word>
  <word wid="834" pos="DT" lemma="the">the</word>
  <word wid="835" pos="NN" lemma="recaptcha">reCAPTCHA</word>
  <word wid="836" pos="IN" lemma="below">below</word>
  <word wid="837" pos="TO" lemma="to">to</word>
  <word wid="838" pos="VB" lemma="join">join</word>
  <word wid="839" pos="PRP$" lemma="we">our</word>
  <word wid="840" pos="NN" lemma="email">email</word>
  <word wid="841" pos="NN" lemma="list">list</word>
  <word wid="842" pos="IN" lemma="about">About</word>
  <word wid="843" pos="JJ" lemma="clir">CLIR</word>
  <word wid="844" pos="NN" lemma="clir">CLIR</word>
  <word wid="845" pos="VBZ" lemma="be">is</word>
  <word wid="846" pos="DT" lemma="a">an</word>
  <word wid="847" pos="JJ" lemma="independent">independent</word>
  <word wid="848" pos="JJ" lemma="nonprofit">nonprofit</word>
  <word wid="849" pos="NN" lemma="organization">organization</word>
  <word wid="850" pos="WDT" lemma="that">that</word>
  <word wid="851" pos="VBZ" lemma="forge">forges</word>
  <word wid="852" pos="NNS" lemma="strategy">strategies</word>
  <word wid="853" pos="TO" lemma="to">to</word>
  <word wid="854" pos="VB" lemma="enhance">enhance</word>
  <word wid="855" pos="NN" lemma="research">research</word>
  <word wid="856" pos="NN" lemma="teaching">teaching</word>
  <word wid="857" pos="CC" lemma="and">and</word>
  <word wid="858" pos="VBG" lemma="learn">learning</word>
  <word wid="859" pos="NNS" lemma="environment">environments</word>
  <word wid="860" pos="IN" lemma="in">in</word>
  <word wid="861" pos="NN" lemma="collaboration">collaboration</word>
  <word wid="862" pos="IN" lemma="with">with</word>
  <word wid="863" pos="NNS" lemma="library">libraries</word>
  <word wid="864" pos="JJ" lemma="cultural">cultural</word>
  <word wid="865" pos="NNS" lemma="institution">institutions</word>
  <word wid="866" pos="CC" lemma="and">and</word>
  <word wid="867" pos="NNS" lemma="community">communities</word>
  <word wid="868" pos="IN" lemma="of">of</word>
  <word wid="869" pos="JJR" lemma="higher">higher</word>
  <word wid="870" pos="VBG" lemma="learn">learning</word>
  <word wid="871" pos="DT" lemma="all">All</word>
  <word wid="872" pos="NN" lemma="content">content</word>
  <word wid="873" pos="IN" lemma="on">on</word>
  <word wid="874" pos="DT" lemma="this">this</word>
  <word wid="875" pos="NN" lemma="site">site</word>
  <word wid="876" pos="VBZ" lemma="be">is</word>
  <word wid="877" pos="JJ" lemma="available">available</word>
  <word wid="878" pos="IN" lemma="for">for</word>
  <word wid="879" pos="NNP" lemma="re">re</word>
  <word wid="880" pos="NN" lemma="use">use</word>
  <word wid="881" pos="IN" lemma="under">under</word>
  <word wid="882" pos="NN" lemma="cc">CC</word>
  <word wid="883" pos="IN" lemma="by">BY</word>
  <word wid="884" pos="NNP" lemma="SA">SA</word>
  <word wid="885" pos="CD" lemma="4">4</word>
  <word wid="886" pos="CD" lemma="0">0</word>
  <word wid="887" pos="NN" lemma="license">License</word>
  <word wid="888" pos="NN" lemma="clir">CLIR</word>
</sentence>
</pos>
