<pos><sentence id="486">
  <word wid="0" pos="JJ" lemma="advanced">Advanced</word>
  <word wid="1" pos="NN" lemma="search">Search</word>
  <word wid="2" pos="IN" lemma="about">About</word>
  <word wid="3" pos="NN" lemma="amp">amp</word>
  <word wid="4" pos="NN" lemma="contact">Contact</word>
  <word wid="5" pos="NN" lemma="browse">Browse</word>
  <word wid="6" pos="NNS" lemma="subject">Subjects</word>
  <word wid="7" pos="NNS" lemma="catalog">Catalogs</word>
  <word wid="8" pos="NNS" lemma="ebook">eBooks</word>
  <word wid="9" pos="NN" lemma="news">News</word>
  <word wid="10" pos="NN" lemma="order">Order</word>
  <word wid="11" pos="NNS" lemma="rights">Rights</word>
  <word wid="12" pos="NNS" lemma="permission">Permissions</word>
  <word wid="13" pos="VBP" lemma="cart">Cart</word>
  <word wid="14" pos="CD" lemma="0">0</word>
  <word wid="15" pos="NNS" lemma="resource">Resources</word>
  <word wid="16" pos="IN" lemma="for">for</word>
  <word wid="17" pos="NNS" lemma="author">Authors</word>
  <word wid="18" pos="NNS" lemma="bookseller">Booksellers</word>
  <word wid="19" pos="NN" lemma="amp">amp</word>
  <word wid="20" pos="NNS" lemma="librarian">Librarians</word>
  <word wid="21" pos="NNS" lemma="educator">Educators</word>
  <word wid="22" pos="NNS" lemma="journalist">Journalists</word>
  <word wid="23" pos="NNS" lemma="reader">Readers</word>
  <word wid="24" pos="NNP" lemma="Emily">Emily</word>
  <word wid="25" pos="NNP" lemma="Dickinson">Dickinson</word>
  <word wid="26" pos="IN" lemma="from">From</word>
  <word wid="27" pos="NNP" lemma="Fascicle">Fascicle</word>
  <word wid="28" pos="TO" lemma="to">to</word>
  <word wid="29" pos="VB" lemma="open">Open</word>
  <word wid="30" pos="NN" lemma="access">Access</word>
  <word wid="31" pos="NNP" lemma="Emily">Emily</word>
  <word wid="32" pos="NNP" lemma="Dickinson">Dickinson</word>
  <word wid="33" pos="CD" lemma="1830">1830</word>
  <word wid="34" pos="CD" lemma="1886">1886</word>
  <word wid="35" pos="VBN" lemma="bequeath">bequeathed</word>
  <word wid="36" pos="TO" lemma="to">to</word>
  <word wid="37" pos="PRP" lemma="we">us</word>
  <word wid="38" pos="RB" lemma="nearly">nearly</word>
  <word wid="39" pos="CD" lemma="1">1</word>
  <word wid="40" pos="CD" lemma="800">800</word>
  <word wid="41" pos="NNS" lemma="poem">poems</word>
  <word wid="42" pos="IN" lemma="in">in</word>
  <word wid="43" pos="DT" lemma="some">some</word>
  <word wid="44" pos="JJ" lemma="passionate">passionate</word>
  <word wid="45" pos="NNS" lemma="year">years</word>
  <word wid="46" pos="PRP" lemma="she">she</word>
  <word wid="47" pos="VBD" lemma="write">wrote</word>
  <word wid="48" pos="RB" lemma="almost">almost</word>
  <word wid="49" pos="DT" lemma="a">a</word>
  <word wid="50" pos="NN" lemma="poem">poem</word>
  <word wid="51" pos="DT" lemma="a">a</word>
  <word wid="52" pos="NN" lemma="day">day</word>
  <word wid="53" pos="IN" lemma="like">Like</word>
  <word wid="54" pos="DT" lemma="all">all</word>
  <word wid="55" pos="JJ" lemma="capacious">capacious</word>
  <word wid="56" pos="NNS" lemma="writer">writers</word>
  <word wid="57" pos="PRP" lemma="she">she</word>
  <word wid="58" pos="VBZ" lemma="baffle">baffles</word>
  <word wid="59" pos="JJ" lemma="complete">complete</word>
  <word wid="60" pos="NN" lemma="understanding">understanding</word>
  <word wid="61" pos="TO" lemma="to">to</word>
  <word wid="62" pos="VB" lemma="enter">enter</word>
  <word wid="63" pos="PRP$" lemma="she">her</word>
  <word wid="64" pos="NNS" lemma="poetic">poetics</word>
  <word wid="65" pos="RB" lemma="entirely">entirely</word>
  <word wid="66" pos="DT" lemma="a">a</word>
  <word wid="67" pos="NN" lemma="reader">reader</word>
  <word wid="68" pos="MD" lemma="would">would</word>
  <word wid="69" pos="VB" lemma="have">have</word>
  <word wid="70" pos="TO" lemma="to">to</word>
  <word wid="71" pos="VB" lemma="know">know</word>
  <word wid="72" pos="IN" lemma="by">by</word>
  <word wid="73" pos="NN" lemma="heart">heart</word>
  <word wid="74" pos="CC" lemma="and">and</word>
  <word wid="75" pos="IN" lemma="by">by</word>
  <word wid="76" pos="NN" lemma="ear">ear</word>
  <word wid="77" pos="DT" lemma="all">all</word>
  <word wid="78" pos="PRP$" lemma="she">her</word>
  <word wid="79" pos="NNS" lemma="poem">poems</word>
  <word wid="80" pos="RB" lemma="ideally">Ideally</word>
  <word wid="81" pos="RB" lemma="too">too</word>
  <word wid="82" pos="PRP$" lemma="she">her</word>
  <word wid="83" pos="NN" lemma="reader">reader</word>
  <word wid="84" pos="MD" lemma="should">should</word>
  <word wid="85" pos="VB" lemma="possess">possess</word>
  <word wid="86" pos="DT" lemma="the">the</word>
  <word wid="87" pos="NNP" lemma="King">King</word>
  <word wid="88" pos="NNP" lemma="James">James</word>
  <word wid="89" pos="NNP" lemma="Bible">Bible</word>
  <word wid="90" pos="IN" lemma="as">as</word>
  <word wid="91" pos="RB" lemma="firmly">firmly</word>
  <word wid="92" pos="IN" lemma="as">as</word>
  <word wid="93" pos="PRP" lemma="she">she</word>
  <word wid="94" pos="VBD" lemma="do">did</word>
  <word wid="95" pos="CC" lemma="and">and</word>
  <word wid="96" pos="MD" lemma="should">should</word>
  <word wid="97" pos="VB" lemma="have">have</word>
  <word wid="98" pos="VBN" lemma="read">read</word>
  <word wid="99" pos="DT" lemma="the">the</word>
  <word wid="100" pos="NN" lemma="poetry">poetry</word>
  <word wid="101" pos="IN" lemma="of">of</word>
  <word wid="102" pos="DT" lemma="the">the</word>
  <word wid="103" pos="NNP" lemma="English">English</word>
  <word wid="104" pos="NN" lemma="past">past</word>
  <word wid="105" pos="IN" lemma="as">as</word>
  <word wid="106" pos="RB" lemma="fervently">fervently</word>
  <word wid="107" pos="IN" lemma="as">as</word>
  <word wid="108" pos="PRP" lemma="she">she</word>
  <word wid="109" pos="VBD" lemma="have">had</word>
  <word wid="110" pos="RB" lemma="yet">Yet</word>
  <word wid="111" pos="NNS" lemma="reader">readers</word>
  <word wid="112" pos="RB" lemma="worldwide">worldwide</word>
  <word wid="113" pos="RB" lemma="even">even</word>
  <word wid="114" pos="WRB" lemma="when">when</word>
  <word wid="115" pos="PRP" lemma="they">they</word>
  <word wid="116" pos="VBP" lemma="have">have</word>
  <word wid="117" pos="VBN" lemma="lack">lacked</word>
  <word wid="118" pos="PRP$" lemma="she">her</word>
  <word wid="119" pos="NN" lemma="background">background</word>
  <word wid="120" pos="VBP" lemma="have">have</word>
  <word wid="121" pos="VBN" lemma="flock">flocked</word>
  <word wid="122" pos="TO" lemma="to">to</word>
  <word wid="123" pos="PRP$" lemma="she">her</word>
  <word wid="124" pos="NNS" lemma="poem">poems</word>
  <word wid="125" pos="VBG" lemma="respond">responding</word>
  <word wid="126" pos="TO" lemma="to">to</word>
  <word wid="127" pos="PRP$" lemma="she">her</word>
  <word wid="128" pos="NN" lemma="candor">candor</word>
  <word wid="129" pos="PRP$" lemma="she">her</word>
  <word wid="130" pos="NN" lemma="grief">grief</word>
  <word wid="131" pos="CC" lemma="and">and</word>
  <word wid="132" pos="PRP$" lemma="she">her</word>
  <word wid="133" pos="NN" lemma="wit">wit</word>
  <word wid="134" pos="NNP" lemma="Helen">Helen</word>
  <word wid="135" pos="NNP" lemma="Vendler">Vendler</word>
  <word wid="136" pos="NNP" lemma="Dickinson">Dickinson</word>
  <word wid="137" pos="VBD" lemma="select">Selected</word>
  <word wid="138" pos="NNS" lemma="poem">Poems</word>
  <word wid="139" pos="CC" lemma="and">and</word>
  <word wid="140" pos="NNS" lemma="commentary">Commentaries</word>
  <word wid="141" pos="NN" lemma="image">image</word>
  <word wid="142" pos="NNP" lemma="Emily">Emily</word>
  <word wid="143" pos="NNP" lemma="Dickinson">Dickinson</word>
  <word wid="144" pos="NNP" lemma="s">s</word>
  <word wid="145" pos="VBG" lemma="write">writing</word>
  <word wid="146" pos="NN" lemma="table">table</word>
  <word wid="147" pos="CC" lemma="and">and</word>
  <word wid="148" pos="NN" lemma="chair">chair</word>
  <word wid="149" pos="IN" lemma="on">on</word>
  <word wid="150" pos="NN" lemma="display">display</word>
  <word wid="151" pos="IN" lemma="in">in</word>
  <word wid="152" pos="DT" lemma="the">the</word>
  <word wid="153" pos="NNP" lemma="Houghton">Houghton</word>
  <word wid="154" pos="NNP" lemma="Library">Library</word>
  <word wid="155" pos="NNP" lemma="s">s</word>
  <word wid="156" pos="NNP" lemma="Dickinson">Dickinson</word>
  <word wid="157" pos="NN" lemma="room">Room</word>
  <word wid="158" pos="NNP" lemma="Emily">Emily</word>
  <word wid="159" pos="NNP" lemma="Dickinson">Dickinson</word>
  <word wid="160" pos="NNP" lemma="s">s</word>
  <word wid="161" pos="VBG" lemma="write">writing</word>
  <word wid="162" pos="NN" lemma="table">table</word>
  <word wid="163" pos="CC" lemma="and">and</word>
  <word wid="164" pos="NN" lemma="chair">chair</word>
  <word wid="165" pos="IN" lemma="on">on</word>
  <word wid="166" pos="NN" lemma="display">display</word>
  <word wid="167" pos="IN" lemma="in">in</word>
  <word wid="168" pos="DT" lemma="the">the</word>
  <word wid="169" pos="NNP" lemma="Houghton">Houghton</word>
  <word wid="170" pos="NNP" lemma="Library">Library</word>
  <word wid="171" pos="NNP" lemma="s">s</word>
  <word wid="172" pos="NNP" lemma="Dickinson">Dickinson</word>
  <word wid="173" pos="NN" lemma="room">Room</word>
  <word wid="174" pos="IN" lemma="in">In</word>
  <word wid="175" pos="CD" lemma="1950">1950</word>
  <word wid="176" pos="NNP" lemma="Harvard">Harvard</word>
  <word wid="177" pos="NNS" lemma="s">s</word>
  <word wid="178" pos="NNP" lemma="Houghton">Houghton</word>
  <word wid="179" pos="NNP" lemma="Library">Library</word>
  <word wid="180" pos="VBD" lemma="receive">received</word>
  <word wid="181" pos="PRP$" lemma="its">its</word>
  <word wid="182" pos="NN" lemma="world">world</word>
  <word wid="183" pos="VBN" lemma="renown">renowned</word>
  <word wid="184" pos="NNP" lemma="Dickinson">Dickinson</word>
  <word wid="185" pos="NN" lemma="collection">Collection</word>
  <word wid="186" pos="IN" lemma="as">as</word>
  <word wid="187" pos="DT" lemma="a">a</word>
  <word wid="188" pos="NN" lemma="gift">gift</word>
  <word wid="189" pos="IN" lemma="from">from</word>
  <word wid="190" pos="DT" lemma="the">the</word>
  <word wid="191" pos="NN" lemma="poet">poet</word>
  <word wid="192" pos="NNS" lemma="s">s</word>
  <word wid="193" pos="NNS" lemma="heir">heirs</word>
  <word wid="194" pos="RB" lemma="together">together</word>
  <word wid="195" pos="IN" lemma="with">with</word>
  <word wid="196" pos="NN" lemma="publication">publication</word>
  <word wid="197" pos="NNS" lemma="rights">rights</word>
  <word wid="198" pos="RB" lemma="soon">Soon</word>
  <word wid="199" pos="RB" lemma="thereafter">thereafter</word>
  <word wid="200" pos="DT" lemma="the">the</word>
  <word wid="201" pos="RB" lemma="well">well</word>
  <word wid="202" pos="VBN" lemma="know">known</word>
  <word wid="203" pos="JJ" lemma="literary">literary</word>
  <word wid="204" pos="NN" lemma="historian">historian</word>
  <word wid="205" pos="NNP" lemma="Thomas">Thomas</word>
  <word wid="206" pos="NNP" lemma="H">H</word>
  <word wid="207" pos="NNP" lemma="Johnson">Johnson</word>
  <word wid="208" pos="VBD" lemma="be">was</word>
  <word wid="209" pos="VBN" lemma="choose">chosen</word>
  <word wid="210" pos="IN" lemma="as">as</word>
  <word wid="211" pos="NN" lemma="editor">editor</word>
  <word wid="212" pos="CC" lemma="and">and</word>
  <word wid="213" pos="DT" lemma="the">the</word>
  <word wid="214" pos="CD" lemma="three">three</word>
  <word wid="215" pos="NN" lemma="volume">volume</word>
  <word wid="216" pos="NNS" lemma="poem">Poems</word>
  <word wid="217" pos="IN" lemma="of">of</word>
  <word wid="218" pos="NNP" lemma="Emily">Emily</word>
  <word wid="219" pos="NNP" lemma="Dickinson">Dickinson</word>
  <word wid="220" pos="VBD" lemma="be">was</word>
  <word wid="221" pos="VBN" lemma="publish">published</word>
  <word wid="222" pos="IN" lemma="by">by</word>
  <word wid="223" pos="NNP" lemma="Harvard">Harvard</word>
  <word wid="224" pos="NNP" lemma="University">University</word>
  <word wid="225" pos="NN" lemma="press">Press</word>
  <word wid="226" pos="IN" lemma="in">in</word>
  <word wid="227" pos="CD" lemma="1955">1955</word>
  <word wid="228" pos="DT" lemma="this">This</word>
  <word wid="229" pos="JJ" lemma="landmark">landmark</word>
  <word wid="230" pos="NN" lemma="edition">edition</word>
  <word wid="231" pos="VBN" lemma="present">presented</word>
  <word wid="232" pos="IN" lemma="for">for</word>
  <word wid="233" pos="DT" lemma="the">the</word>
  <word wid="234" pos="JJ" lemma="first">first</word>
  <word wid="235" pos="NN" lemma="time">time</word>
  <word wid="236" pos="NNS" lemma="transcription">transcriptions</word>
  <word wid="237" pos="IN" lemma="of">of</word>
  <word wid="238" pos="DT" lemma="all">all</word>
  <word wid="239" pos="IN" lemma="of">of</word>
  <word wid="240" pos="NNP" lemma="Dickinson">Dickinson</word>
  <word wid="241" pos="NNS" lemma="s">s</word>
  <word wid="242" pos="VBN" lemma="know">known</word>
  <word wid="243" pos="NNS" lemma="poem">poems</word>
  <word wid="244" pos="VBG" lemma="note">noting</word>
  <word wid="245" pos="JJ" lemma="variant">variant</word>
  <word wid="246" pos="NNS" lemma="word">words</word>
  <word wid="247" pos="CC" lemma="and">and</word>
  <word wid="248" pos="VBG" lemma="include">including</word>
  <word wid="249" pos="JJ" lemma="multiple">multiple</word>
  <word wid="250" pos="NNS" lemma="version">versions</word>
  <word wid="251" pos="IN" lemma="of">of</word>
  <word wid="252" pos="NNS" lemma="poem">poems</word>
  <word wid="253" pos="IN" lemma="in">In</word>
  <word wid="254" pos="CD" lemma="1958">1958</word>
  <word wid="255" pos="DT" lemma="the">the</word>
  <word wid="256" pos="NN" lemma="press">Press</word>
  <word wid="257" pos="VBD" lemma="follow">followed</word>
  <word wid="258" pos="RP" lemma="up">up</word>
  <word wid="259" pos="IN" lemma="with">with</word>
  <word wid="260" pos="DT" lemma="a">a</word>
  <word wid="261" pos="CD" lemma="three">three</word>
  <word wid="262" pos="NN" lemma="volume">volume</word>
  <word wid="263" pos="NN" lemma="edition">edition</word>
  <word wid="264" pos="IN" lemma="of">of</word>
  <word wid="265" pos="NNP" lemma="Dickinson">Dickinson</word>
  <word wid="266" pos="NNP" lemma="s">s</word>
  <word wid="267" pos="NNS" lemma="letter">letters</word>
  <word wid="268" pos="VBN" lemma="edit">edited</word>
  <word wid="269" pos="IN" lemma="by">by</word>
  <word wid="270" pos="NNP" lemma="Johnson">Johnson</word>
  <word wid="271" pos="CC" lemma="and">and</word>
  <word wid="272" pos="NNP" lemma="Theodora">Theodora</word>
  <word wid="273" pos="NNP" lemma="Ward">Ward</word>
  <word wid="274" pos="IN" lemma="in">In</word>
  <word wid="275" pos="CD" lemma="1998">1998</word>
  <word wid="276" pos="NN" lemma="r">R</word>
  <word wid="277" pos="NN" lemma="w">W</word>
  <word wid="278" pos="NNP" lemma="Franklin">Franklin</word>
  <word wid="279" pos="CC" lemma="and">and</word>
  <word wid="280" pos="DT" lemma="the">the</word>
  <word wid="281" pos="NN" lemma="press">Press</word>
  <word wid="282" pos="VBD" lemma="publish">published</word>
  <word wid="283" pos="DT" lemma="a">a</word>
  <word wid="284" pos="JJ" lemma="new">new</word>
  <word wid="285" pos="CD" lemma="three">three</word>
  <word wid="286" pos="NN" lemma="volume">volume</word>
  <word wid="287" pos="NN" lemma="edition">edition</word>
  <word wid="288" pos="VBG" lemma="contain">containing</word>
  <word wid="289" pos="CD" lemma="1">1</word>
  <word wid="290" pos="CD" lemma="789">789</word>
  <word wid="291" pos="IN" lemma="of">of</word>
  <word wid="292" pos="NNP" lemma="Dickinson">Dickinson</word>
  <word wid="293" pos="NNP" lemma="s">s</word>
  <word wid="294" pos="VBZ" lemma="poem">poems</word>
  <word wid="295" pos="DT" lemma="the">the</word>
  <word wid="296" pos="JJS" lemma="largest">largest</word>
  <word wid="297" pos="NN" lemma="number">number</word>
  <word wid="298" pos="RB" lemma="ever">ever</word>
  <word wid="299" pos="VBN" lemma="assemble">assembled</word>
  <word wid="300" pos="VBN" lemma="arrange">Arranged</word>
  <word wid="301" pos="RB" lemma="chronologically">chronologically</word>
  <word wid="302" pos="VBN" lemma="base">based</word>
  <word wid="303" pos="IN" lemma="on">on</word>
  <word wid="304" pos="JJ" lemma="new">new</word>
  <word wid="305" pos="VBG" lemma="date">dating</word>
  <word wid="306" pos="NN" lemma="analysis">analysis</word>
  <word wid="307" pos="DT" lemma="the">The</word>
  <word wid="308" pos="NNS" lemma="poem">Poems</word>
  <word wid="309" pos="IN" lemma="of">of</word>
  <word wid="310" pos="NNP" lemma="Emily">Emily</word>
  <word wid="311" pos="NNP" lemma="Dickinson">Dickinson</word>
  <word wid="312" pos="NNP" lemma="Variorum">Variorum</word>
  <word wid="313" pos="NN" lemma="edition">Edition</word>
  <word wid="314" pos="VBN" lemma="transcribe">transcribed</word>
  <word wid="315" pos="DT" lemma="the">the</word>
  <word wid="316" pos="JJ" lemma="entire">entire</word>
  <word wid="317" pos="JJ" lemma="known">known</word>
  <word wid="318" pos="NN" lemma="corpus">corpus</word>
  <word wid="319" pos="IN" lemma="of">of</word>
  <word wid="320" pos="RB" lemma="approximately">approximately</word>
  <word wid="321" pos="CD" lemma="2">2</word>
  <word wid="322" pos="CD" lemma="500">500</word>
  <word wid="323" pos="JJ" lemma="textual">textual</word>
  <word wid="324" pos="NNS" lemma="source">sources</word>
  <word wid="325" pos="VBG" lemma="give">giving</word>
  <word wid="326" pos="IN" lemma="as">as</word>
  <word wid="327" pos="JJ" lemma="many">many</word>
  <word wid="328" pos="IN" lemma="as">as</word>
  <word wid="329" pos="CD" lemma="seven">seven</word>
  <word wid="330" pos="NNS" lemma="version">versions</word>
  <word wid="331" pos="IN" lemma="of">of</word>
  <word wid="332" pos="DT" lemma="some">some</word>
  <word wid="333" pos="NNS" lemma="poem">poems</word>
  <word wid="334" pos="IN" lemma="in">In</word>
  <word wid="335" pos="CD" lemma="1999">1999</word>
  <word wid="336" pos="DT" lemma="the">the</word>
  <word wid="337" pos="NN" lemma="press">Press</word>
  <word wid="338" pos="VBN" lemma="publish">published</word>
  <word wid="339" pos="NNP" lemma="Franklin">Franklin</word>
  <word wid="340" pos="VBZ" lemma="be">s</word>
  <word wid="341" pos="DT" lemma="the">The</word>
  <word wid="342" pos="NNS" lemma="poem">Poems</word>
  <word wid="343" pos="IN" lemma="of">of</word>
  <word wid="344" pos="NNP" lemma="Emily">Emily</word>
  <word wid="345" pos="NNP" lemma="Dickinson">Dickinson</word>
  <word wid="346" pos="NNP" lemma="Reading">Reading</word>
  <word wid="347" pos="NN" lemma="edition">Edition</word>
  <word wid="348" pos="WDT" lemma="which">which</word>
  <word wid="349" pos="VBZ" lemma="follow">follows</word>
  <word wid="350" pos="DT" lemma="the">the</word>
  <word wid="351" pos="JJ" lemma="same">same</word>
  <word wid="352" pos="NN" lemma="numbering">numbering</word>
  <word wid="353" pos="NN" lemma="system">system</word>
  <word wid="354" pos="IN" lemma="as">as</word>
  <word wid="355" pos="DT" lemma="the">the</word>
  <word wid="356" pos="NN" lemma="variorum">Variorum</word>
  <word wid="357" pos="CC" lemma="but">but</word>
  <word wid="358" pos="VBZ" lemma="offer">offers</word>
  <word wid="359" pos="IN" lemma="in">in</word>
  <word wid="360" pos="CD" lemma="one">one</word>
  <word wid="361" pos="NN" lemma="volume">volume</word>
  <word wid="362" pos="DT" lemma="a">a</word>
  <word wid="363" pos="JJ" lemma="single">single</word>
  <word wid="364" pos="NN" lemma="version">version</word>
  <word wid="365" pos="IN" lemma="of">of</word>
  <word wid="366" pos="DT" lemma="each">each</word>
  <word wid="367" pos="NN" lemma="poem">poem</word>
  <word wid="368" pos="IN" lemma="in">In</word>
  <word wid="369" pos="CD" lemma="2016">2016</word>
  <word wid="370" pos="DT" lemma="the">the</word>
  <word wid="371" pos="NN" lemma="press">Press</word>
  <word wid="372" pos="VBN" lemma="publish">published</word>
  <word wid="373" pos="NNP" lemma="Cristanne">Cristanne</word>
  <word wid="374" pos="NNP" lemma="Miller">Miller</word>
  <word wid="375" pos="NNP" lemma="s">s</word>
  <word wid="376" pos="NN" lemma="edition">edition</word>
  <word wid="377" pos="IN" lemma="of">of</word>
  <word wid="378" pos="NNP" lemma="Emily">Emily</word>
  <word wid="379" pos="NNP" lemma="Dickinson">Dickinson</word>
  <word wid="380" pos="VBZ" lemma="be">s</word>
  <word wid="381" pos="NNS" lemma="poem">Poems</word>
  <word wid="382" pos="IN" lemma="as">As</word>
  <word wid="383" pos="PRP" lemma="she">She</word>
  <word wid="384" pos="VBD" lemma="preserve">Preserved</word>
  <word wid="385" pos="PRP" lemma="they">Them</word>
  <word wid="386" pos="DT" lemma="this">This</word>
  <word wid="387" pos="VBZ" lemma="be">is</word>
  <word wid="388" pos="DT" lemma="the">the</word>
  <word wid="389" pos="RB" lemma="only">only</word>
  <word wid="390" pos="JJ" lemma="major">major</word>
  <word wid="391" pos="NN" lemma="edition">edition</word>
  <word wid="392" pos="IN" lemma="of">of</word>
  <word wid="393" pos="DT" lemma="the">the</word>
  <word wid="394" pos="JJ" lemma="complete">complete</word>
  <word wid="395" pos="NNS" lemma="poem">poems</word>
  <word wid="396" pos="TO" lemma="to">to</word>
  <word wid="397" pos="VB" lemma="distinguish">distinguish</word>
  <word wid="398" pos="IN" lemma="in">in</word>
  <word wid="399" pos="JJ" lemma="easy">easy</word>
  <word wid="400" pos="JJ" lemma="visual">visual</word>
  <word wid="401" pos="NN" lemma="form">form</word>
  <word wid="402" pos="DT" lemma="the">the</word>
  <word wid="403" pos="RB" lemma="approximately">approximately</word>
  <word wid="404" pos="CD" lemma="1">1</word>
  <word wid="405" pos="CD" lemma="100">100</word>
  <word wid="406" pos="NNS" lemma="poem">poems</word>
  <word wid="407" pos="NNP" lemma="Dickinson">Dickinson</word>
  <word wid="408" pos="VBD" lemma="take">took</word>
  <word wid="409" pos="NNS" lemma="pain">pains</word>
  <word wid="410" pos="TO" lemma="to">to</word>
  <word wid="411" pos="VB" lemma="copy">copy</word>
  <word wid="412" pos="RB" lemma="carefully">carefully</word>
  <word wid="413" pos="IN" lemma="onto">onto</word>
  <word wid="414" pos="VBN" lemma="fold">folded</word>
  <word wid="415" pos="NNS" lemma="sheet">sheets</word>
  <word wid="416" pos="CC" lemma="and">and</word>
  <word wid="417" pos="VB" lemma="gather">gather</word>
  <word wid="418" pos="IN" lemma="with">with</word>
  <word wid="419" pos="NN" lemma="string">string</word>
  <word wid="420" pos="IN" lemma="into">into</word>
  <word wid="421" pos="NNS" lemma="booklet">booklets</word>
  <word wid="422" pos="NNS" lemma="fascicle">fascicles</word>
  <word wid="423" pos="RB" lemma="arguably">arguably</word>
  <word wid="424" pos="TO" lemma="to">to</word>
  <word wid="425" pos="VB" lemma="preserve">preserve</word>
  <word wid="426" pos="PRP" lemma="they">them</word>
  <word wid="427" pos="IN" lemma="for">for</word>
  <word wid="428" pos="NN" lemma="posterity">posterity</word>
  <word wid="429" pos="IN" lemma="from">from</word>
  <word wid="430" pos="DT" lemma="the">the</word>
  <word wid="431" pos="NNS" lemma="poem">poems</word>
  <word wid="432" pos="PRP" lemma="she">she</word>
  <word wid="433" pos="VBD" lemma="keep">kept</word>
  <word wid="434" pos="IN" lemma="in">in</word>
  <word wid="435" pos="JJR" lemma="rougher">rougher</word>
  <word wid="436" pos="NN" lemma="form">form</word>
  <word wid="437" pos="CC" lemma="or">or</word>
  <word wid="438" pos="RB" lemma="apparently">apparently</word>
  <word wid="439" pos="VBD" lemma="do">did</word>
  <word wid="440" pos="RB" lemma="not">not</word>
  <word wid="441" pos="VB" lemma="retain">retain</word>
  <word wid="442" pos="NNP" lemma="Miller">Miller</word>
  <word wid="443" pos="NNP" lemma="s">s</word>
  <word wid="444" pos="NN" lemma="introduction">Introduction</word>
  <word wid="445" pos="VBZ" lemma="describe">describes</word>
  <word wid="446" pos="NNP" lemma="Dickinson">Dickinson</word>
  <word wid="447" pos="NNP" lemma="s">s</word>
  <word wid="448" pos="NNS" lemma="practice">practices</word>
  <word wid="449" pos="IN" lemma="in">in</word>
  <word wid="450" pos="NN" lemma="copying">copying</word>
  <word wid="451" pos="CC" lemma="and">and</word>
  <word wid="452" pos="VBG" lemma="circulate">circulating</word>
  <word wid="453" pos="NNS" lemma="poem">poems</word>
  <word wid="454" pos="CC" lemma="and">and</word>
  <word wid="455" pos="VBZ" lemma="summarize">summarizes</word>
  <word wid="456" pos="JJ" lemma="contentious">contentious</word>
  <word wid="457" pos="NNS" lemma="debate">debates</word>
  <word wid="458" pos="IN" lemma="within">within</word>
  <word wid="459" pos="NNP" lemma="Dickinson">Dickinson</word>
  <word wid="460" pos="NN" lemma="scholarship">scholarship</word>
  <word wid="461" pos="NN" lemma="hup">HUP</word>
  <word wid="462" pos="NNS" lemma="s">s</word>
  <word wid="463" pos="RB" lemma="long">long</word>
  <word wid="464" pos="NN" lemma="engagement">engagement</word>
  <word wid="465" pos="IN" lemma="with">with</word>
  <word wid="466" pos="DT" lemma="the">the</word>
  <word wid="467" pos="NNS" lemma="work">works</word>
  <word wid="468" pos="IN" lemma="of">of</word>
  <word wid="469" pos="NNP" lemma="Emily">Emily</word>
  <word wid="470" pos="NNP" lemma="Dickinson">Dickinson</word>
  <word wid="471" pos="VBZ" lemma="extend">extends</word>
  <word wid="472" pos="TO" lemma="to">to</word>
  <word wid="473" pos="DT" lemma="the">the</word>
  <word wid="474" pos="NNP" lemma="Emily">Emily</word>
  <word wid="475" pos="NNP" lemma="Dickinson">Dickinson</word>
  <word wid="476" pos="NNP" lemma="Archive">Archive</word>
  <word wid="477" pos="WDT" lemma="which">which</word>
  <word wid="478" pos="VBZ" lemma="make">makes</word>
  <word wid="479" pos="JJ" lemma="high">high</word>
  <word wid="480" pos="NN" lemma="resolution">resolution</word>
  <word wid="481" pos="NNS" lemma="image">images</word>
  <word wid="482" pos="IN" lemma="of">of</word>
  <word wid="483" pos="NNS" lemma="manuscript">manuscripts</word>
  <word wid="484" pos="IN" lemma="of">of</word>
  <word wid="485" pos="NNP" lemma="Dickinson">Dickinson</word>
  <word wid="486" pos="NNP" lemma="s">s</word>
  <word wid="487" pos="NNP" lemma="poetry">poetry</word>
  <word wid="488" pos="CC" lemma="and">and</word>
  <word wid="489" pos="NNS" lemma="letter">letters</word>
  <word wid="490" pos="JJ" lemma="available">available</word>
  <word wid="491" pos="IN" lemma="in">in</word>
  <word wid="492" pos="JJ" lemma="open">open</word>
  <word wid="493" pos="NN" lemma="access">access</word>
  <word wid="494" pos="IN" lemma="along">along</word>
  <word wid="495" pos="IN" lemma="with">with</word>
  <word wid="496" pos="NNS" lemma="transcription">transcriptions</word>
  <word wid="497" pos="CC" lemma="and">and</word>
  <word wid="498" pos="NNS" lemma="annotation">annotations</word>
  <word wid="499" pos="IN" lemma="from">from</word>
  <word wid="500" pos="JJ" lemma="historical">historical</word>
  <word wid="501" pos="CC" lemma="and">and</word>
  <word wid="502" pos="JJ" lemma="scholarly">scholarly</word>
  <word wid="503" pos="NNS" lemma="edition">editions</word>
  <word wid="504" pos="DT" lemma="the">The</word>
  <word wid="505" pos="JJ" lemma="first">first</word>
  <word wid="506" pos="NN" lemma="release">release</word>
  <word wid="507" pos="IN" lemma="in">in</word>
  <word wid="508" pos="NN" lemma="fall">Fall</word>
  <word wid="509" pos="CD" lemma="2013">2013</word>
  <word wid="510" pos="VBZ" lemma="focus">focuses</word>
  <word wid="511" pos="IN" lemma="on">on</word>
  <word wid="512" pos="DT" lemma="the">the</word>
  <word wid="513" pos="NN" lemma="corpus">corpus</word>
  <word wid="514" pos="IN" lemma="of">of</word>
  <word wid="515" pos="NNS" lemma="poem">poems</word>
  <word wid="516" pos="WDT" lemma="that">that</word>
  <word wid="517" pos="NNP" lemma="Franklin">Franklin</word>
  <word wid="518" pos="VBD" lemma="identify">identified</word>
  <word wid="519" pos="IN" lemma="in">in</word>
  <word wid="520" pos="PRP$" lemma="he">his</word>
  <word wid="521" pos="NN" lemma="variorum">Variorum</word>
  <word wid="522" pos="CC" lemma="but">but</word>
  <word wid="523" pos="VBZ" lemma="include">includes</word>
  <word wid="524" pos="NNS" lemma="transcription">transcriptions</word>
  <word wid="525" pos="IN" lemma="by">by</word>
  <word wid="526" pos="NNP" lemma="Johnson">Johnson</word>
  <word wid="527" pos="CC" lemma="and">and</word>
  <word wid="528" pos="JJ" lemma="other">other</word>
  <word wid="529" pos="NNS" lemma="editor">editors</word>
  <word wid="530" pos="WP" lemma="who">who</word>
  <word wid="531" pos="VBD" lemma="publish">published</word>
  <word wid="532" pos="NNP" lemma="Dickinson">Dickinson</word>
  <word wid="533" pos="NNP" lemma="s">s</word>
  <word wid="534" pos="NNS" lemma="poem">poems</word>
  <word wid="535" pos="IN" lemma="in">in</word>
  <word wid="536" pos="NNS" lemma="collection">collections</word>
  <word wid="537" pos="VBG" lemma="start">starting</word>
  <word wid="538" pos="RB" lemma="shortly">shortly</word>
  <word wid="539" pos="IN" lemma="after">after</word>
  <word wid="540" pos="PRP$" lemma="she">her</word>
  <word wid="541" pos="NN" lemma="death">death</word>
  <word wid="542" pos="IN" lemma="under">Under</word>
  <word wid="543" pos="DT" lemma="the">the</word>
  <word wid="544" pos="NN" lemma="guidance">guidance</word>
  <word wid="545" pos="IN" lemma="of">of</word>
  <word wid="546" pos="JJ" lemma="general">General</word>
  <word wid="547" pos="NN" lemma="editor">Editor</word>
  <word wid="548" pos="NNP" lemma="Leslie">Leslie</word>
  <word wid="549" pos="NNP" lemma="Morris">Morris</word>
  <word wid="550" pos="IN" lemma="with">with</word>
  <word wid="551" pos="DT" lemma="a">an</word>
  <word wid="552" pos="JJ" lemma="advisory">Advisory</word>
  <word wid="553" pos="NN" lemma="board">Board</word>
  <word wid="554" pos="IN" lemma="of">of</word>
  <word wid="555" pos="JJ" lemma="distinguished">distinguished</word>
  <word wid="556" pos="NNS" lemma="scholar">scholars</word>
  <word wid="557" pos="NNP" lemma="EDA">EDA</word>
  <word wid="558" pos="VBZ" lemma="be">is</word>
  <word wid="559" pos="DT" lemma="a">a</word>
  <word wid="560" pos="VBG" lemma="grow">growing</word>
  <word wid="561" pos="NN" lemma="collaboration">collaboration</word>
  <word wid="562" pos="WDT" lemma="that">that</word>
  <word wid="563" pos="VBZ" lemma="include">includes</word>
  <word wid="564" pos="NNP" lemma="Amherst">Amherst</word>
  <word wid="565" pos="NNP" lemma="College">College</word>
  <word wid="566" pos="NNP" lemma="Beinecke">Beinecke</word>
  <word wid="567" pos="NN" lemma="library">Library</word>
  <word wid="568" pos="IN" lemma="at">at</word>
  <word wid="569" pos="NNP" lemma="Yale">Yale</word>
  <word wid="570" pos="NNP" lemma="University">University</word>
  <word wid="571" pos="DT" lemma="the">the</word>
  <word wid="572" pos="NNP" lemma="Berkman">Berkman</word>
  <word wid="573" pos="NNP" lemma="Center">Center</word>
  <word wid="574" pos="IN" lemma="for">for</word>
  <word wid="575" pos="NNP" lemma="Internet">Internet</word>
  <word wid="576" pos="CC" lemma="and">and</word>
  <word wid="577" pos="NNP" lemma="Society">Society</word>
  <word wid="578" pos="IN" lemma="at">at</word>
  <word wid="579" pos="NNP" lemma="Harvard">Harvard</word>
  <word wid="580" pos="NNP" lemma="Boston">Boston</word>
  <word wid="581" pos="NNP" lemma="Public">Public</word>
  <word wid="582" pos="NNP" lemma="Library">Library</word>
  <word wid="583" pos="NNP" lemma="Digital">Digital</word>
  <word wid="584" pos="NNP" lemma="Public">Public</word>
  <word wid="585" pos="NNP" lemma="Library">Library</word>
  <word wid="586" pos="IN" lemma="of">of</word>
  <word wid="587" pos="NNP" lemma="America">America</word>
  <word wid="588" pos="NNP" lemma="Emily">Emily</word>
  <word wid="589" pos="NNP" lemma="Dickinson">Dickinson</word>
  <word wid="590" pos="NN" lemma="lexicon">Lexicon</word>
  <word wid="591" pos="IN" lemma="at">at</word>
  <word wid="592" pos="NNP" lemma="Brigham">Brigham</word>
  <word wid="593" pos="NNP" lemma="Young">Young</word>
  <word wid="594" pos="NNP" lemma="University">University</word>
  <word wid="595" pos="NNP" lemma="Harvard">Harvard</word>
  <word wid="596" pos="NN" lemma="library">Library</word>
  <word wid="597" pos="NNP" lemma="Harvard">Harvard</word>
  <word wid="598" pos="NNP" lemma="University">University</word>
  <word wid="599" pos="NN" lemma="press">Press</word>
  <word wid="600" pos="CC" lemma="and">and</word>
  <word wid="601" pos="NNP" lemma="Houghton">Houghton</word>
  <word wid="602" pos="NN" lemma="library">Library</word>
  <word wid="603" pos="IN" lemma="at">at</word>
  <word wid="604" pos="NNP" lemma="Harvard">Harvard</word>
  <word wid="605" pos="NNP" lemma="Key">Key</word>
  <word wid="606" pos="NNS" lemma="feature">Features</word>
  <word wid="607" pos="IN" lemma="of">of</word>
  <word wid="608" pos="NNP" lemma="Emily">Emily</word>
  <word wid="609" pos="NNP" lemma="Dickinson">Dickinson</word>
  <word wid="610" pos="NNP" lemma="Archive">Archive</word>
  <word wid="611" pos="VB" lemma="find">Find</word>
  <word wid="612" pos="NNS" lemma="poem">poems</word>
  <word wid="613" pos="RB" lemma="easily">easily</word>
  <word wid="614" pos="IN" lemma="with">with</word>
  <word wid="615" pos="JJ" lemma="multiple">multiple</word>
  <word wid="616" pos="NN" lemma="index">index</word>
  <word wid="617" pos="CC" lemma="and">and</word>
  <word wid="618" pos="NN" lemma="reference">reference</word>
  <word wid="619" pos="NNS" lemma="tool">tools</word>
  <word wid="620" pos="VB" lemma="study">Study</word>
  <word wid="621" pos="DT" lemma="the">the</word>
  <word wid="622" pos="NN" lemma="poet">poet</word>
  <word wid="623" pos="NNS" lemma="s">s</word>
  <word wid="624" pos="JJ" lemma="own">own</word>
  <word wid="625" pos="NN" lemma="handwriting">handwriting</word>
  <word wid="626" pos="NNS" lemma="variant">variants</word>
  <word wid="627" pos="CC" lemma="and">and</word>
  <word wid="628" pos="NN" lemma="arrangement">arrangement</word>
  <word wid="629" pos="IN" lemma="of">of</word>
  <word wid="630" pos="PRP$" lemma="she">her</word>
  <word wid="631" pos="NN" lemma="work">work</word>
  <word wid="632" pos="VB" lemma="read">Read</word>
  <word wid="633" pos="CC" lemma="and">and</word>
  <word wid="634" pos="VB" lemma="compare">compare</word>
  <word wid="635" pos="NNS" lemma="edition">editions</word>
  <word wid="636" pos="NN" lemma="word">word</word>
  <word wid="637" pos="NN" lemma="choice">choice</word>
  <word wid="638" pos="CC" lemma="and">and</word>
  <word wid="639" pos="NNS" lemma="transcription">transcriptions</word>
  <word wid="640" pos="IN" lemma="through">through</word>
  <word wid="641" pos="NN" lemma="time">time</word>
  <word wid="642" pos="VB" lemma="engage">Engage</word>
  <word wid="643" pos="IN" lemma="in">in</word>
  <word wid="644" pos="JJ" lemma="new">new</word>
  <word wid="645" pos="NN" lemma="scholarship">scholarship</word>
  <word wid="646" pos="VBG" lemma="use">using</word>
  <word wid="647" pos="NNS" lemma="tool">tools</word>
  <word wid="648" pos="IN" lemma="for">for</word>
  <word wid="649" pos="VBG" lemma="create">creating</word>
  <word wid="650" pos="NNS" lemma="annotation">annotations</word>
  <word wid="651" pos="NNS" lemma="transcription">transcriptions</word>
  <word wid="652" pos="CC" lemma="and">and</word>
  <word wid="653" pos="VBG" lemma="read">reading</word>
  <word wid="654" pos="NNS" lemma="list">lists</word>
  <word wid="655" pos="NN" lemma="image">image</word>
  <word wid="656" pos="NN" lemma="cover">Cover</word>
  <word wid="657" pos="NNP" lemma="Emily">Emily</word>
  <word wid="658" pos="NNP" lemma="Dickinson">Dickinson</word>
  <word wid="659" pos="VBZ" lemma="be">s</word>
  <word wid="660" pos="NNS" lemma="poem">Poems</word>
  <word wid="661" pos="IN" lemma="as">As</word>
  <word wid="662" pos="PRP" lemma="she">She</word>
  <word wid="663" pos="VBD" lemma="preserve">Preserved</word>
  <word wid="664" pos="PRP" lemma="they">Them</word>
  <word wid="665" pos="NNP" lemma="Emily">Emily</word>
  <word wid="666" pos="NNP" lemma="Dickinson">Dickinson</word>
  <word wid="667" pos="VBZ" lemma="be">s</word>
  <word wid="668" pos="NNS" lemma="poem">Poems</word>
  <word wid="669" pos="IN" lemma="as">As</word>
  <word wid="670" pos="PRP" lemma="she">She</word>
  <word wid="671" pos="VBD" lemma="preserve">Preserved</word>
  <word wid="672" pos="PRP" lemma="they">Them</word>
  <word wid="673" pos="VBN" lemma="edit">Edited</word>
  <word wid="674" pos="IN" lemma="by">by</word>
  <word wid="675" pos="NNP" lemma="Cristanne">Cristanne</word>
  <word wid="676" pos="NNP" lemma="Miller">Miller</word>
  <word wid="677" pos="NN" lemma="image">image</word>
  <word wid="678" pos="NN" lemma="cover">Cover</word>
  <word wid="679" pos="NNP" lemma="Dickinson">Dickinson</word>
  <word wid="680" pos="VBD" lemma="select">Selected</word>
  <word wid="681" pos="NNS" lemma="poem">Poems</word>
  <word wid="682" pos="CC" lemma="and">and</word>
  <word wid="683" pos="NNS" lemma="commentary">Commentaries</word>
  <word wid="684" pos="NNP" lemma="Dickinson">Dickinson</word>
  <word wid="685" pos="VBD" lemma="select">Selected</word>
  <word wid="686" pos="NNS" lemma="poem">Poems</word>
  <word wid="687" pos="CC" lemma="and">and</word>
  <word wid="688" pos="NNS" lemma="commentary">Commentaries</word>
  <word wid="689" pos="NNP" lemma="Helen">Helen</word>
  <word wid="690" pos="NNP" lemma="Vendler">Vendler</word>
  <word wid="691" pos="NN" lemma="image">image</word>
  <word wid="692" pos="VB" lemma="cover">Cover</word>
  <word wid="693" pos="DT" lemma="the">The</word>
  <word wid="694" pos="NNS" lemma="garden">Gardens</word>
  <word wid="695" pos="IN" lemma="of">of</word>
  <word wid="696" pos="NNP" lemma="Emily">Emily</word>
  <word wid="697" pos="NNP" lemma="Dickinson">Dickinson</word>
  <word wid="698" pos="DT" lemma="the">The</word>
  <word wid="699" pos="NNS" lemma="garden">Gardens</word>
  <word wid="700" pos="IN" lemma="of">of</word>
  <word wid="701" pos="NNP" lemma="Emily">Emily</word>
  <word wid="702" pos="NNP" lemma="Dickinson">Dickinson</word>
  <word wid="703" pos="NNP" lemma="Judith">Judith</word>
  <word wid="704" pos="NNP" lemma="Farr">Farr</word>
  <word wid="705" pos="NN" lemma="image">image</word>
  <word wid="706" pos="VB" lemma="cover">Cover</word>
  <word wid="707" pos="DT" lemma="the">The</word>
  <word wid="708" pos="NNS" lemma="poem">Poems</word>
  <word wid="709" pos="IN" lemma="of">of</word>
  <word wid="710" pos="NNP" lemma="Emily">Emily</word>
  <word wid="711" pos="NNP" lemma="Dickinson">Dickinson</word>
  <word wid="712" pos="NNP" lemma="Reading">Reading</word>
  <word wid="713" pos="NN" lemma="edition">Edition</word>
  <word wid="714" pos="DT" lemma="the">The</word>
  <word wid="715" pos="NNS" lemma="poem">Poems</word>
  <word wid="716" pos="IN" lemma="of">of</word>
  <word wid="717" pos="NNP" lemma="Emily">Emily</word>
  <word wid="718" pos="NNP" lemma="Dickinson">Dickinson</word>
  <word wid="719" pos="NNP" lemma="Reading">Reading</word>
  <word wid="720" pos="NN" lemma="edition">Edition</word>
  <word wid="721" pos="VBN" lemma="edit">Edited</word>
  <word wid="722" pos="IN" lemma="by">by</word>
  <word wid="723" pos="NN" lemma="r">R</word>
  <word wid="724" pos="NN" lemma="w">W</word>
  <word wid="725" pos="NNP" lemma="Franklin">Franklin</word>
  <word wid="726" pos="NNP" lemma="View">View</word>
  <word wid="727" pos="JJ" lemma="additional">additional</word>
  <word wid="728" pos="NNS" lemma="work">works</word>
  <word wid="729" pos="IN" lemma="by">by</word>
  <word wid="730" pos="CC" lemma="and">and</word>
  <word wid="731" pos="IN" lemma="about">about</word>
  <word wid="732" pos="NNP" lemma="Emily">Emily</word>
  <word wid="733" pos="NNP" lemma="Dickinson">Dickinson</word>
  <word wid="734" pos="IN" lemma="from">from</word>
  <word wid="735" pos="NNP" lemma="Harvard">Harvard</word>
  <word wid="736" pos="NNP" lemma="University">University</word>
  <word wid="737" pos="NNP" lemma="Press">Press</word>
  <word wid="738" pos="RB" lemma="back">Back</word>
  <word wid="739" pos="TO" lemma="to">to</word>
  <word wid="740" pos="JJ" lemma="top">top</word>
  <word wid="741" pos="NN" lemma="image">image</word>
  <word wid="742" pos="NN" lemma="hup">HUP</word>
  <word wid="743" pos="IN" lemma="on">on</word>
  <word wid="744" pos="NNP" lemma="YouTube">YouTube</word>
  <word wid="745" pos="NN" lemma="abstract">abstract</word>
  <word wid="746" pos="NN" lemma="logo">logo</word>
  <word wid="747" pos="NN" lemma="design">design</word>
  <word wid="748" pos="JJ" lemma="recent">Recent</word>
  <word wid="749" pos="NN" lemma="news">News</word>
  <word wid="750" pos="DT" lemma="the">The</word>
  <word wid="751" pos="NN" lemma="economist">Economist</word>
  <word wid="752" pos="VBN" lemma="use">used</word>
  <word wid="753" pos="NNS" lemma="datum">data</word>
  <word wid="754" pos="IN" lemma="from">from</word>
  <word wid="755" pos="NNP" lemma="Richard">Richard</word>
  <word wid="756" pos="NNP" lemma="H">H</word>
  <word wid="757" pos="NNP" lemma="Sander">Sander</word>
  <word wid="758" pos="FW" lemma="et">et</word>
  <word wid="759" pos="NNP" lemma="al">al</word>
  <word wid="760" pos="NNP" lemma="s">s</word>
  <word wid="761" pos="VBG" lemma="move">Moving</word>
  <word wid="762" pos="IN" lemma="toward">toward</word>
  <word wid="763" pos="NN" lemma="integration">Integration</word>
  <word wid="764" pos="DT" lemma="the">The</word>
  <word wid="765" pos="NN" lemma="past">Past</word>
  <word wid="766" pos="CC" lemma="and">and</word>
  <word wid="767" pos="NN" lemma="future">Future</word>
  <word wid="768" pos="IN" lemma="of">of</word>
  <word wid="769" pos="JJ" lemma="fair">Fair</word>
  <word wid="770" pos="NN" lemma="housing">Housing</word>
  <word wid="771" pos="IN" lemma="in">in</word>
  <word wid="772" pos="DT" lemma="a">a</word>
  <word wid="773" pos="NN" lemma="report">report</word>
  <word wid="774" pos="IN" lemma="on">on</word>
  <word wid="775" pos="WRB" lemma="how">how</word>
  <word wid="776" pos="NN" lemma="class">class</word>
  <word wid="777" pos="VBN" lemma="base">based</word>
  <word wid="778" pos="VBZ" lemma="have">has</word>
  <word wid="779" pos="RB" lemma="quietly">quietly</word>
  <word wid="780" pos="VBN" lemma="replace">replaced</word>
  <word wid="781" pos="NN" lemma="race">race</word>
  <word wid="782" pos="VBN" lemma="base">based</word>
  <word wid="783" pos="NN" lemma="segregation">segregation</word>
  <word wid="784" pos="IN" lemma="in">in</word>
  <word wid="785" pos="NNP" lemma="America">America</word>
  <word wid="786" pos="CC" lemma="and">and</word>
  <word wid="787" pos="IN" lemma="in">in</word>
  <word wid="788" pos="DT" lemma="a">an</word>
  <word wid="789" pos="VBN" lemma="associate">associated</word>
  <word wid="790" pos="JJ" lemma="interactive">interactive</word>
  <word wid="791" pos="NN" lemma="feature">feature</word>
  <word wid="792" pos="NNP" lemma="Samuel">Samuel</word>
  <word wid="793" pos="NNP" lemma="Moyn">Moyn</word>
  <word wid="794" pos="NN" lemma="author">author</word>
  <word wid="795" pos="IN" lemma="of">of</word>
  <word wid="796" pos="RB" lemma="not">Not</word>
  <word wid="797" pos="JJ" lemma="enough">Enough</word>
  <word wid="798" pos="JJ" lemma="human">Human</word>
  <word wid="799" pos="NNS" lemma="rights">Rights</word>
  <word wid="800" pos="IN" lemma="in">in</word>
  <word wid="801" pos="DT" lemma="a">an</word>
  <word wid="802" pos="JJ" lemma="unequal">Unequal</word>
  <word wid="803" pos="NN" lemma="world">World</word>
  <word wid="804" pos="VBD" lemma="argue">argued</word>
  <word wid="805" pos="IN" lemma="in">in</word>
  <word wid="806" pos="JJ" lemma="foreign">Foreign</word>
  <word wid="807" pos="NN" lemma="policy">Policy</word>
  <word wid="808" pos="IN" lemma="that">that</word>
  <word wid="809" pos="PRP" lemma="it">it</word>
  <word wid="810" pos="VBZ" lemma="be">is</word>
  <word wid="811" pos="JJ" lemma="shortsighted">shortsighted</word>
  <word wid="812" pos="IN" lemma="for">for</word>
  <word wid="813" pos="DT" lemma="the">the</word>
  <word wid="814" pos="NNP" lemma="U">U</word>
  <word wid="815" pos="NNP" lemma="S">S</word>
  <word wid="816" pos="TO" lemma="to">to</word>
  <word wid="817" pos="VB" lemma="promote">promote</word>
  <word wid="818" pos="JJ" lemma="basic">basic</word>
  <word wid="819" pos="NNS" lemma="rights">rights</word>
  <word wid="820" pos="IN" lemma="without">without</word>
  <word wid="821" pos="DT" lemma="a">a</word>
  <word wid="822" pos="JJR" lemma="broader">broader</word>
  <word wid="823" pos="NN" lemma="effort">effort</word>
  <word wid="824" pos="TO" lemma="to">to</word>
  <word wid="825" pos="VB" lemma="combat">combat</word>
  <word wid="826" pos="DT" lemma="the">the</word>
  <word wid="827" pos="JJ" lemma="entrenched">entrenched</word>
  <word wid="828" pos="JJ" lemma="economic">economic</word>
  <word wid="829" pos="NN" lemma="inequality">inequality</word>
  <word wid="830" pos="WDT" lemma="that">that</word>
  <word wid="831" pos="VBZ" lemma="endanger">endangers</word>
  <word wid="832" pos="PRP" lemma="they">them</word>
  <word wid="833" pos="NN" lemma="vera">Vera</word>
  <word wid="834" pos="NNP" lemma="Tobin">Tobin</word>
  <word wid="835" pos="NN" lemma="author">author</word>
  <word wid="836" pos="IN" lemma="of">of</word>
  <word wid="837" pos="NNS" lemma="element">Elements</word>
  <word wid="838" pos="IN" lemma="of">of</word>
  <word wid="839" pos="NN" lemma="surprise">Surprise</word>
  <word wid="840" pos="PRP$" lemma="we">Our</word>
  <word wid="841" pos="JJ" lemma="mental">Mental</word>
  <word wid="842" pos="NNS" lemma="limit">Limits</word>
  <word wid="843" pos="CC" lemma="and">and</word>
  <word wid="844" pos="DT" lemma="the">the</word>
  <word wid="845" pos="NNS" lemma="satisfaction">Satisfactions</word>
  <word wid="846" pos="IN" lemma="of">of</word>
  <word wid="847" pos="NN" lemma="plot">Plot</word>
  <word wid="848" pos="VBD" lemma="discuss">discussed</word>
  <word wid="849" pos="WRB" lemma="how">how</word>
  <word wid="850" pos="PRP$" lemma="we">our</word>
  <word wid="851" pos="NNS" lemma="brain">brains</word>
  <word wid="852" pos="NN" lemma="process">process</word>
  <word wid="853" pos="NNS" lemma="surprise">surprises</word>
  <word wid="854" pos="IN" lemma="in">in</word>
  <word wid="855" pos="JJ" lemma="real">real</word>
  <word wid="856" pos="NN" lemma="life">life</word>
  <word wid="857" pos="CC" lemma="and">and</word>
  <word wid="858" pos="IN" lemma="in">in</word>
  <word wid="859" pos="DT" lemma="the">the</word>
  <word wid="860" pos="JJS" lemma="juiciest">juiciest</word>
  <word wid="861" pos="NN" lemma="genre">genre</word>
  <word wid="862" pos="NN" lemma="fiction">fiction</word>
  <word wid="863" pos="IN" lemma="on">on</word>
  <word wid="864" pos="DT" lemma="the">the</word>
  <word wid="865" pos="NN" lemma="podcast">podcast</word>
  <word wid="866" pos="JJ" lemma="smart">Smart</word>
  <word wid="867" pos="NNS" lemma="bitch">Bitches</word>
  <word wid="868" pos="JJ" lemma="trashy">Trashy</word>
  <word wid="869" pos="NNS" lemma="book">Books</word>
  <word wid="870" pos="NNP" lemma="Henry">Henry</word>
  <word wid="871" pos="NNP" lemma="Greely">Greely</word>
  <word wid="872" pos="NN" lemma="author">author</word>
  <word wid="873" pos="IN" lemma="of">of</word>
  <word wid="874" pos="DT" lemma="the">The</word>
  <word wid="875" pos="NN" lemma="end">End</word>
  <word wid="876" pos="IN" lemma="of">of</word>
  <word wid="877" pos="NN" lemma="sex">Sex</word>
  <word wid="878" pos="CC" lemma="and">and</word>
  <word wid="879" pos="DT" lemma="the">the</word>
  <word wid="880" pos="NN" lemma="future">Future</word>
  <word wid="881" pos="IN" lemma="of">of</word>
  <word wid="882" pos="JJ" lemma="human">Human</word>
  <word wid="883" pos="NNP" lemma="Reproduction">Reproduction</word>
  <word wid="884" pos="VBD" lemma="speak">spoke</word>
  <word wid="885" pos="IN" lemma="with">with</word>
  <word wid="886" pos="NNP" lemma="Maclean">Maclean</word>
  <word wid="887" pos="VBZ" lemma="be">s</word>
  <word wid="888" pos="IN" lemma="about">about</word>
  <word wid="889" pos="DT" lemma="the">the</word>
  <word wid="890" pos="JJ" lemma="legal">legal</word>
  <word wid="891" pos="JJ" lemma="ethical">ethical</word>
  <word wid="892" pos="CC" lemma="and">and</word>
  <word wid="893" pos="JJ" lemma="moral">moral</word>
  <word wid="894" pos="NNS" lemma="issue">issues</word>
  <word wid="895" pos="WDT" lemma="that">that</word>
  <word wid="896" pos="MD" lemma="will">will</word>
  <word wid="897" pos="VB" lemma="arise">arise</word>
  <word wid="898" pos="RB" lemma="once">once</word>
  <word wid="899" pos="NN" lemma="lab">lab</word>
  <word wid="900" pos="VBN" lemma="grow">grown</word>
  <word wid="901" pos="JJ" lemma="human">human</word>
  <word wid="902" pos="NNS" lemma="embryo">embryos</word>
  <word wid="903" pos="VBP" lemma="become">become</word>
  <word wid="904" pos="DT" lemma="the">the</word>
  <word wid="905" pos="NN" lemma="norm">norm</word>
  <word wid="906" pos="RB" lemma="rather">rather</word>
  <word wid="907" pos="IN" lemma="than">than</word>
  <word wid="908" pos="DT" lemma="the">the</word>
  <word wid="909" pos="NN" lemma="exception">exception</word>
  <word wid="910" pos="NN" lemma="stay">Stay</word>
  <word wid="911" pos="VBD" lemma="post">Posted</word>
  <word wid="912" pos="NN" lemma="image">image</word>
  <word wid="913" pos="NN" lemma="cover">Cover</word>
  <word wid="914" pos="IN" lemma="of">of</word>
  <word wid="915" pos="JJ" lemma="current">current</word>
  <word wid="916" pos="JJ" lemma="seasonal">seasonal</word>
  <word wid="917" pos="NN" lemma="catalog">catalog</word>
  <word wid="918" pos="VB" lemma="browse">Browse</word>
  <word wid="919" pos="PRP$" lemma="we">our</word>
  <word wid="920" pos="JJ" lemma="interactive">interactive</word>
  <word wid="921" pos="NN" lemma="spring">Spring</word>
  <word wid="922" pos="NN" lemma="summer">Summer</word>
  <word wid="923" pos="CD" lemma="2018">2018</word>
  <word wid="924" pos="NN" lemma="catalog">catalog</word>
  <word wid="925" pos="RB" lemma="now">Now</word>
  <word wid="926" pos="JJ" lemma="available">Available</word>
  <word wid="927" pos="DT" lemma="the">The</word>
  <word wid="928" pos="NNP" lemma="digital">digital</word>
  <word wid="929" pos="NNP" lemma="Loeb">Loeb</word>
  <word wid="930" pos="JJ" lemma="classical">Classical</word>
  <word wid="931" pos="NN" lemma="library">Library</word>
  <word wid="932" pos="NNS" lemma="loebclassic">loebclassics</word>
  <word wid="933" pos="NN" lemma="com">com</word>
  <word wid="934" pos="VBZ" lemma="extend">extends</word>
  <word wid="935" pos="DT" lemma="the">the</word>
  <word wid="936" pos="NN" lemma="founding">founding</word>
  <word wid="937" pos="NN" lemma="mission">mission</word>
  <word wid="938" pos="IN" lemma="of">of</word>
  <word wid="939" pos="NNP" lemma="James">James</word>
  <word wid="940" pos="NNP" lemma="Loeb">Loeb</word>
  <word wid="941" pos="IN" lemma="with">with</word>
  <word wid="942" pos="DT" lemma="a">an</word>
  <word wid="943" pos="JJ" lemma="interconnected">interconnected</word>
  <word wid="944" pos="RB" lemma="fully">fully</word>
  <word wid="945" pos="JJ" lemma="searchable">searchable</word>
  <word wid="946" pos="RB" lemma="perpetually">perpetually</word>
  <word wid="947" pos="VBG" lemma="grow">growing</word>
  <word wid="948" pos="JJ" lemma="virtual">virtual</word>
  <word wid="949" pos="NN" lemma="library">library</word>
  <word wid="950" pos="IN" lemma="of">of</word>
  <word wid="951" pos="DT" lemma="all">all</word>
  <word wid="952" pos="DT" lemma="that">that</word>
  <word wid="953" pos="VBZ" lemma="be">is</word>
  <word wid="954" pos="JJ" lemma="important">important</word>
  <word wid="955" pos="IN" lemma="in">in</word>
  <word wid="956" pos="JJ" lemma="greek">Greek</word>
  <word wid="957" pos="CC" lemma="and">and</word>
  <word wid="958" pos="JJ" lemma="latin">Latin</word>
  <word wid="959" pos="NN" lemma="literature">literature</word>
  <word wid="960" pos="VB" lemma="find">Find</word>
  <word wid="961" pos="JJ" lemma="new">new</word>
  <word wid="962" pos="VBG" lemma="face">facing</word>
  <word wid="963" pos="NN" lemma="page">page</word>
  <word wid="964" pos="NNS" lemma="translation">translations</word>
  <word wid="965" pos="IN" lemma="of">of</word>
  <word wid="966" pos="JJ" lemma="classic">classic</word>
  <word wid="967" pos="NNS" lemma="work">works</word>
  <word wid="968" pos="IN" lemma="from">from</word>
  <word wid="969" pos="DT" lemma="the">the</word>
  <word wid="970" pos="NNP" lemma="Dumbarton">Dumbarton</word>
  <word wid="971" pos="NNP" lemma="Oaks">Oaks</word>
  <word wid="972" pos="JJ" lemma="medieval">Medieval</word>
  <word wid="973" pos="NN" lemma="library">Library</word>
  <word wid="974" pos="PRP" lemma="I">I</word>
  <word wid="975" pos="VBP" lemma="tatti">Tatti</word>
  <word wid="976" pos="NNP" lemma="Renaissance">Renaissance</word>
  <word wid="977" pos="NNP" lemma="Library">Library</word>
  <word wid="978" pos="NNP" lemma="Loeb">Loeb</word>
  <word wid="979" pos="JJ" lemma="classical">Classical</word>
  <word wid="980" pos="NN" lemma="library">Library</word>
  <word wid="981" pos="CC" lemma="and">and</word>
  <word wid="982" pos="NN" lemma="murty">Murty</word>
  <word wid="983" pos="JJ" lemma="classical">Classical</word>
  <word wid="984" pos="NN" lemma="library">Library</word>
  <word wid="985" pos="IN" lemma="of">of</word>
  <word wid="986" pos="NNP" lemma="India">India</word>
  <word wid="987" pos="NNPS" lemma="Booksellers">Booksellers</word>
  <word wid="988" pos="CC" lemma="and">and</word>
  <word wid="989" pos="NNPS" lemma="Librarians">Librarians</word>
  <word wid="990" pos="PRP$" lemma="we">Our</word>
  <word wid="991" pos="JJ" lemma="recent">recent</word>
  <word wid="992" pos="NNS" lemma="title">titles</word>
  <word wid="993" pos="VBP" lemma="be">are</word>
  <word wid="994" pos="JJ" lemma="available">available</word>
  <word wid="995" pos="IN" lemma="via">via</word>
  <word wid="996" pos="NNP" lemma="Edelweiss">Edelweiss</word>
  <word wid="997" pos="IN" lemma="off">Off</word>
  <word wid="998" pos="DT" lemma="the">the</word>
  <word wid="999" pos="NN" lemma="page">Page</word>
  <word wid="1000" pos="NN" lemma="visit">Visit</word>
  <word wid="1001" pos="PRP$" lemma="we">our</word>
  <word wid="1002" pos="NNS" lemma="multimedia">multimedia</word>
  <word wid="1003" pos="NN" lemma="page">page</word>
  <word wid="1004" pos="IN" lemma="for">for</word>
  <word wid="1005" pos="NN" lemma="video">video</word>
  <word wid="1006" pos="IN" lemma="about">about</word>
  <word wid="1007" pos="JJ" lemma="recent">recent</word>
  <word wid="1008" pos="NNS" lemma="project">projects</word>
  <word wid="1009" pos="CC" lemma="and">and</word>
  <word wid="1010" pos="NNS" lemma="interview">interviews</word>
  <word wid="1011" pos="IN" lemma="with">with</word>
  <word wid="1012" pos="NNP" lemma="HUP">HUP</word>
  <word wid="1013" pos="NNS" lemma="author">authors</word>
  <word wid="1014" pos="VB" lemma="join">Join</word>
  <word wid="1015" pos="PRP$" lemma="we">Our</word>
  <word wid="1016" pos="NN" lemma="mailing">Mailing</word>
  <word wid="1017" pos="NN" lemma="list">List</word>
  <word wid="1018" pos="VBP" lemma="subscribe">Subscribe</word>
  <word wid="1019" pos="TO" lemma="to">to</word>
  <word wid="1020" pos="VB" lemma="receive">receive</word>
  <word wid="1021" pos="NN" lemma="information">information</word>
  <word wid="1022" pos="IN" lemma="about">about</word>
  <word wid="1023" pos="JJ" lemma="forthcoming">forthcoming</word>
  <word wid="1024" pos="NNS" lemma="book">books</word>
  <word wid="1025" pos="JJ" lemma="seasonal">seasonal</word>
  <word wid="1026" pos="NNS" lemma="catalog">catalogs</word>
  <word wid="1027" pos="CC" lemma="and">and</word>
  <word wid="1028" pos="JJR" lemma="more">more</word>
  <word wid="1029" pos="IN" lemma="in">in</word>
  <word wid="1030" pos="NNS" lemma="newsletter">newsletters</word>
  <word wid="1031" pos="VBN" lemma="tailor">tailored</word>
  <word wid="1032" pos="TO" lemma="to">to</word>
  <word wid="1033" pos="PRP$" lemma="you">your</word>
  <word wid="1034" pos="NNS" lemma="interest">interests</word>
  <word wid="1035" pos="NN" lemma="blog">Blog</word>
  <word wid="1036" pos="NN" lemma="image">image</word>
  <word wid="1037" pos="NN" lemma="blockchain">Blockchain</word>
  <word wid="1038" pos="CC" lemma="and">and</word>
  <word wid="1039" pos="DT" lemma="the">the</word>
  <word wid="1040" pos="NN" lemma="law">Law</word>
  <word wid="1041" pos="NNP" lemma="April">April</word>
  <word wid="1042" pos="CD" lemma="10">10</word>
  <word wid="1043" pos="DT" lemma="the">The</word>
  <word wid="1044" pos="NN" lemma="rule">Rule</word>
  <word wid="1045" pos="IN" lemma="of">of</word>
  <word wid="1046" pos="NN" lemma="code">Code</word>
  <word wid="1047" pos="CC" lemma="vs">vs</word>
  <word wid="1048" pos="DT" lemma="the">The</word>
  <word wid="1049" pos="NN" lemma="rule">Rule</word>
  <word wid="1050" pos="IN" lemma="of">of</word>
  <word wid="1051" pos="NN" lemma="law">Law</word>
  <word wid="1052" pos="WRB" lemma="when">When</word>
  <word wid="1053" pos="NNP" lemma="Satoshi">Satoshi</word>
  <word wid="1054" pos="NNP" lemma="Nakamoto">Nakamoto</word>
  <word wid="1055" pos="VBD" lemma="release">released</word>
  <word wid="1056" pos="NN" lemma="bitcoin">Bitcoin</word>
  <word wid="1057" pos="TO" lemma="to">to</word>
  <word wid="1058" pos="DT" lemma="the">the</word>
  <word wid="1059" pos="NN" lemma="world">world</word>
  <word wid="1060" pos="PRP" lemma="he">he</word>
  <word wid="1061" pos="VBD" lemma="have">had</word>
  <word wid="1062" pos="DT" lemma="a">a</word>
  <word wid="1063" pos="JJ" lemma="clear">clear</word>
  <word wid="1064" pos="NN" lemma="idea">idea</word>
  <word wid="1065" pos="IN" lemma="in">in</word>
  <word wid="1066" pos="NN" lemma="mind">mind</word>
  <word wid="1067" pos="WDT" lemma="which">which</word>
  <word wid="1068" pos="VBD" lemma="be">was</word>
  <word wid="1069" pos="VBN" lemma="reflect">reflected</word>
  <word wid="1070" pos="IN" lemma="in">in</word>
  <word wid="1071" pos="DT" lemma="the">the</word>
  <word wid="1072" pos="NN" lemma="message">message</word>
  <word wid="1073" pos="PRP" lemma="he">he</word>
  <word wid="1074" pos="VBD" lemma="include">included</word>
  <word wid="1075" pos="IN" lemma="in">in</word>
  <word wid="1076" pos="NN" lemma="bitcoin">Bitcoin</word>
  <word wid="1077" pos="NNS" lemma="s">s</word>
  <word wid="1078" pos="NN" lemma="genesis">genesis</word>
  <word wid="1079" pos="VBP" lemma="block">block</word>
  <word wid="1080" pos="DT" lemma="the">The</word>
  <word wid="1081" pos="NNS" lemma="time">Times</word>
  <word wid="1082" pos="NN" lemma="03">03</word>
  <word wid="1083" pos="NNP" lemma="Jan">Jan</word>
  <word wid="1084" pos="CD" lemma="2009">2009</word>
  <word wid="1085" pos="NNP" lemma="Chancellor">Chancellor</word>
  <word wid="1086" pos="IN" lemma="on">on</word>
  <word wid="1087" pos="NNP" lemma="brink">brink</word>
  <word wid="1088" pos="IN" lemma="of">of</word>
  <word wid="1089" pos="JJ" lemma="second">second</word>
  <word wid="1090" pos="NN" lemma="bailout">bailout</word>
  <word wid="1091" pos="IN" lemma="for">for</word>
  <word wid="1092" pos="NNS" lemma="bank">banks</word>
  <word wid="1093" pos="NNP" lemma="Nakamoto">Nakamoto</word>
  <word wid="1094" pos="VBD" lemma="release">released</word>
  <word wid="1095" pos="DT" lemma="the">the</word>
  <word wid="1096" pos="NNP" lemma="Bitcoin">Bitcoin</word>
  <word wid="1097" pos="NN" lemma="network">network</word>
  <word wid="1098" pos="IN" lemma="in">in</word>
  <word wid="1099" pos="DT" lemma="the">the</word>
  <word wid="1100" pos="NN" lemma="middle">middle</word>
  <word wid="1101" pos="IN" lemma="of">of</word>
  <word wid="1102" pos="DT" lemma="a">a</word>
  <word wid="1103" pos="JJ" lemma="financial">financial</word>
  <word wid="1104" pos="NN" lemma="crisis">crisis</word>
  <word wid="1105" pos="IN" lemma="as">as</word>
  <word wid="1106" pos="DT" lemma="a">a</word>
  <word wid="1107" pos="NN" lemma="reaction">reaction</word>
  <word wid="1108" pos="TO" lemma="to">to</word>
  <word wid="1109" pos="DT" lemma="a">an</word>
  <word wid="1110" pos="JJ" lemma="unstable">unstable</word>
  <word wid="1111" pos="JJ" lemma="international">international</word>
  <word wid="1112" pos="NN" lemma="banking">banking</word>
  <word wid="1113" pos="NN" lemma="system">system</word>
  <word wid="1114" pos="IN" lemma="in">In</word>
  <word wid="1115" pos="VBG" lemma="do">doing</word>
  <word wid="1116" pos="RB" lemma="so">so</word>
  <word wid="1117" pos="PRP" lemma="he">he</word>
  <word wid="1118" pos="VBD" lemma="give">gave</word>
  <word wid="1119" pos="NN" lemma="birth">birth</word>
  <word wid="1120" pos="TO" lemma="to">to</word>
  <word wid="1121" pos="DT" lemma="a">a</word>
  <word wid="1122" pos="JJ" lemma="new">new</word>
  <word wid="1123" pos="NN" lemma="currency">currency</word>
  <word wid="1124" pos="CD" lemma="one">one</word>
  <word wid="1125" pos="VBN" lemma="control">controlled</word>
  <word wid="1126" pos="RB" lemma="not">not</word>
  <word wid="1127" pos="IN" lemma="by">by</word>
  <word wid="1128" pos="DT" lemma="any">any</word>
  <word wid="1129" pos="NN" lemma="government">government</word>
  <word wid="1130" pos="CC" lemma="or">or</word>
  <word wid="1131" pos="JJ" lemma="central">central</word>
  <word wid="1132" pos="NN" lemma="bank">bank</word>
  <word wid="1133" pos="CC" lemma="but">but</word>
  <word wid="1134" pos="RB" lemma="only">only</word>
  <word wid="1135" pos="IN" lemma="by">by</word>
  <word wid="1136" pos="NN" lemma="cryptography">cryptography</word>
  <word wid="1137" pos="CC" lemma="and">and</word>
  <word wid="1138" pos="NN" lemma="code">code</word>
  <word wid="1139" pos="IN" lemma="as">As</word>
  <word wid="1140" pos="DT" lemma="a">a</word>
  <word wid="1141" pos="JJ" lemma="global">global</word>
  <word wid="1142" pos="CC" lemma="and">and</word>
  <word wid="1143" pos="JJ" lemma="decentralized">decentralized</word>
  <word wid="1144" pos="NN" lemma="payment">payment</word>
  <word wid="1145" pos="NN" lemma="system">system</word>
  <word wid="1146" pos="WDT" lemma="that">that</word>
  <word wid="1147" pos="VBZ" lemma="operate">operates</word>
  <word wid="1148" pos="IN" lemma="without">without</word>
  <word wid="1149" pos="VBN" lemma="centralize">centralized</word>
  <word wid="1150" pos="NN" lemma="control">control</word>
  <word wid="1151" pos="NN" lemma="bitcoin">Bitcoin</word>
  <word wid="1152" pos="VBD" lemma="hold">held</word>
  <word wid="1153" pos="RP" lemma="out">out</word>
  <word wid="1154" pos="DT" lemma="the">the</word>
  <word wid="1155" pos="NN" lemma="hope">hope</word>
  <word wid="1156" pos="IN" lemma="of">of</word>
  <word wid="1157" pos="JJ" lemma="newfound">newfound</word>
  <word wid="1158" pos="JJ" lemma="economic">economic</word>
  <word wid="1159" pos="NN" lemma="freedom">freedom</word>
  <word wid="1160" pos="IN" lemma="for">for</word>
  <word wid="1161" pos="DT" lemma="those">those</word>
  <word wid="1162" pos="JJ" lemma="dubious">dubious</word>
  <word wid="1163" pos="IN" lemma="of">of</word>
  <word wid="1164" pos="JJ" lemma="governmental">governmental</word>
  <word wid="1165" pos="NN" lemma="authority">authority</word>
  <word wid="1166" pos="JJ" lemma="early">Early</word>
  <word wid="1167" pos="NN" lemma="bitcoin">Bitcoin</word>
  <word wid="1168" pos="NNS" lemma="adopter">adopters</word>
  <word wid="1169" pos="VBD" lemma="subscribe">subscribed</word>
  <word wid="1170" pos="TO" lemma="to">to</word>
  <word wid="1171" pos="DT" lemma="the">the</word>
  <word wid="1172" pos="NN" lemma="notion">notion</word>
  <word wid="1173" pos="IN" lemma="of">of</word>
  <word wid="1174" pos="NNS" lemma="vire">vires</word>
  <word wid="1175" pos="IN" lemma="in">in</word>
  <word wid="1176" pos="JJ" lemma="numeris">numeris</word>
  <word wid="1177" pos="NN" lemma="strength">strength</word>
  <word wid="1178" pos="IN" lemma="in">in</word>
  <word wid="1179" pos="NNS" lemma="number">numbers</word>
  <word wid="1180" pos="DT" lemma="a">a</word>
  <word wid="1181" pos="NN" lemma="motto">motto</word>
  <word wid="1182" pos="IN" lemma="about">About</word>
  <word wid="1183" pos="NN" lemma="amp">amp</word>
  <word wid="1184" pos="NN" lemma="contact">Contact</word>
  <word wid="1185" pos="NNS" lemma="award">Awards</word>
  <word wid="1186" pos="VBP" lemma="browse">Browse</word>
  <word wid="1187" pos="NNS" lemma="catalog">Catalogs</word>
  <word wid="1188" pos="NN" lemma="conference">Conference</word>
  <word wid="1189" pos="VBZ" lemma="exhibit">Exhibits</word>
  <word wid="1190" pos="NNS" lemma="ebook">eBooks</word>
  <word wid="1191" pos="NN" lemma="exam">Exam</word>
  <word wid="1192" pos="NNS" lemma="copy">Copies</word>
  <word wid="1193" pos="NN" lemma="news">News</word>
  <word wid="1194" pos="NN" lemma="order">Order</word>
  <word wid="1195" pos="NNS" lemma="rights">Rights</word>
  <word wid="1196" pos="NNS" lemma="permission">Permissions</word>
  <word wid="1197" pos="VB" lemma="search">Search</word>
  <word wid="1198" pos="NN" lemma="shopping">Shopping</word>
  <word wid="1199" pos="NN" lemma="cart">Cart</word>
  <word wid="1200" pos="NNS" lemma="resource">Resources</word>
  <word wid="1201" pos="IN" lemma="for">for</word>
  <word wid="1202" pos="NNS" lemma="author">Authors</word>
  <word wid="1203" pos="NNS" lemma="bookseller">Booksellers</word>
  <word wid="1204" pos="NN" lemma="amp">amp</word>
  <word wid="1205" pos="NNS" lemma="librarian">Librarians</word>
  <word wid="1206" pos="NNS" lemma="educator">Educators</word>
  <word wid="1207" pos="NNS" lemma="journalist">Journalists</word>
  <word wid="1208" pos="NNS" lemma="reader">Readers</word>
  <word wid="1209" pos="NNP" lemma="Harvard">Harvard</word>
  <word wid="1210" pos="NNP" lemma="University">University</word>
  <word wid="1211" pos="NNP" lemma="Press">Press</word>
  <word wid="1212" pos="NNS" lemma="office">offices</word>
  <word wid="1213" pos="VBP" lemma="be">are</word>
  <word wid="1214" pos="JJ" lemma="located">located</word>
  <word wid="1215" pos="IN" lemma="at">at</word>
  <word wid="1216" pos="CD" lemma="79">79</word>
  <word wid="1217" pos="NNP" lemma="Garden">Garden</word>
  <word wid="1218" pos="NNP" lemma="Street">Street</word>
  <word wid="1219" pos="NNP" lemma="Cambridge">Cambridge</word>
  <word wid="1220" pos="NNP" lemma="MA">MA</word>
  <word wid="1221" pos="CD" lemma="02138">02138</word>
  <word wid="1222" pos="NNP" lemma="USA">USA</word>
  <word wid="1223" pos="NN" lemma="amp">amp</word>
  <word wid="1224" pos="NNP" lemma="Vernon">Vernon</word>
  <word wid="1225" pos="NNP" lemma="House">House</word>
  <word wid="1226" pos="CD" lemma="23">23</word>
  <word wid="1227" pos="NNP" lemma="Sicilian">Sicilian</word>
  <word wid="1228" pos="NNP" lemma="Avenue">Avenue</word>
  <word wid="1229" pos="NNP" lemma="London">London</word>
  <word wid="1230" pos="NN" lemma="wc1a">WC1A</word>
  <word wid="1231" pos="JJ" lemma="2qs">2QS</word>
  <word wid="1232" pos="NNP" lemma="UK">UK</word>
  <word wid="1233" pos="CD" lemma="2018">2018</word>
  <word wid="1234" pos="NN" lemma="president">President</word>
  <word wid="1235" pos="CC" lemma="and">and</word>
  <word wid="1236" pos="NNS" lemma="fellow">Fellows</word>
  <word wid="1237" pos="IN" lemma="of">of</word>
  <word wid="1238" pos="NNP" lemma="Harvard">Harvard</word>
  <word wid="1239" pos="NNP" lemma="College">College</word>
  <word wid="1240" pos="VB" lemma="read">Read</word>
  <word wid="1241" pos="PRP$" lemma="we">our</word>
  <word wid="1242" pos="NN" lemma="privacy">Privacy</word>
  <word wid="1243" pos="NN" lemma="policy">Policy</word>
</sentence>
</pos>
