<pos><sentence id="474">
  <word wid="0" pos="VB" lemma="skip">Skip</word>
  <word wid="1" pos="TO" lemma="to">to</word>
  <word wid="2" pos="JJ" lemma="main">main</word>
  <word wid="3" pos="NN" lemma="content">content</word>
  <word wid="4" pos="NN" lemma="bookmark">bookmark</word>
  <word wid="5" pos="NN" lemma="image">image</word>
  <word wid="6" pos="JJ" lemma="main">Main</word>
  <word wid="7" pos="NN" lemma="menu">menu</word>
  <word wid="8" pos="NN" lemma="home">Home</word>
  <word wid="9" pos="IN" lemma="about">About</word>
  <word wid="10" pos="NNS" lemma="sig">SIGs</word>
  <word wid="11" pos="NNS" lemma="publication">Publications</word>
  <word wid="12" pos="NN" lemma="conference">Conference</word>
  <word wid="13" pos="NNS" lemma="award">Awards</word>
  <word wid="14" pos="NNS" lemma="committee">Committees</word>
  <word wid="15" pos="NN" lemma="news">News</word>
  <word wid="16" pos="NNS" lemma="resource">Resources</word>
  <word wid="17" pos="JJ" lemma="adho">ADHO</word>
  <word wid="18" pos="NN" lemma="image">image</word>
  <word wid="19" pos="NN" lemma="adho">ADHO</word>
  <word wid="20" pos="NN" lemma="logo">logo</word>
  <word wid="21" pos="NN" lemma="membership">Membership</word>
  <word wid="22" pos="NNS" lemma="option">options</word>
  <word wid="23" pos="PRP$" lemma="we">Our</word>
  <word wid="24" pos="NN" lemma="mission">Mission</word>
  <word wid="25" pos="DT" lemma="the">The</word>
  <word wid="26" pos="NN" lemma="alliance">Alliance</word>
  <word wid="27" pos="IN" lemma="of">of</word>
  <word wid="28" pos="NNP" lemma="Digital">Digital</word>
  <word wid="29" pos="NNS" lemma="humanities">Humanities</word>
  <word wid="30" pos="NNS" lemma="organization">Organizations</word>
  <word wid="31" pos="NN" lemma="adho">ADHO</word>
  <word wid="32" pos="VBZ" lemma="promote">promotes</word>
  <word wid="33" pos="CC" lemma="and">and</word>
  <word wid="34" pos="VBZ" lemma="support">supports</word>
  <word wid="35" pos="NNP" lemma="digital">digital</word>
  <word wid="36" pos="NNP" lemma="research">research</word>
  <word wid="37" pos="CC" lemma="and">and</word>
  <word wid="38" pos="VBG" lemma="teach">teaching</word>
  <word wid="39" pos="IN" lemma="across">across</word>
  <word wid="40" pos="DT" lemma="all">all</word>
  <word wid="41" pos="NNS" lemma="art">arts</word>
  <word wid="42" pos="CC" lemma="and">and</word>
  <word wid="43" pos="NNS" lemma="humanities">humanities</word>
  <word wid="44" pos="NNS" lemma="discipline">disciplines</word>
  <word wid="45" pos="VBG" lemma="act">acting</word>
  <word wid="46" pos="IN" lemma="as">as</word>
  <word wid="47" pos="DT" lemma="a">a</word>
  <word wid="48" pos="NN" lemma="community">community</word>
  <word wid="49" pos="VBN" lemma="base">based</word>
  <word wid="50" pos="JJ" lemma="advisory">advisory</word>
  <word wid="51" pos="NN" lemma="force">force</word>
  <word wid="52" pos="CC" lemma="and">and</word>
  <word wid="53" pos="VBG" lemma="support">supporting</word>
  <word wid="54" pos="NN" lemma="excellence">excellence</word>
  <word wid="55" pos="IN" lemma="in">in</word>
  <word wid="56" pos="NN" lemma="research">research</word>
  <word wid="57" pos="NN" lemma="publication">publication</word>
  <word wid="58" pos="NN" lemma="collaboration">collaboration</word>
  <word wid="59" pos="CC" lemma="and">and</word>
  <word wid="60" pos="NN" lemma="training">training</word>
  <word wid="61" pos="DT" lemma="the">The</word>
  <word wid="62" pos="VBG" lemma="follow">following</word>
  <word wid="63" pos="NNS" lemma="organization">organizations</word>
  <word wid="64" pos="VBP" lemma="be">are</word>
  <word wid="65" pos="JJ" lemma="current">current</word>
  <word wid="66" pos="NNS" lemma="member">members</word>
  <word wid="67" pos="IN" lemma="of">of</word>
  <word wid="68" pos="NNP" lemma="ADHO">ADHO</word>
  <word wid="69" pos="DT" lemma="the">The</word>
  <word wid="70" pos="NNP" lemma="European">European</word>
  <word wid="71" pos="NNP" lemma="Association">Association</word>
  <word wid="72" pos="IN" lemma="for">for</word>
  <word wid="73" pos="NNP" lemma="Digital">Digital</word>
  <word wid="74" pos="NNS" lemma="humanities">Humanities</word>
  <word wid="75" pos="NNP" lemma="EADH">EADH</word>
  <word wid="76" pos="NNP" lemma="Association">Association</word>
  <word wid="77" pos="IN" lemma="for">for</word>
  <word wid="78" pos="NNS" lemma="computer">Computers</word>
  <word wid="79" pos="CC" lemma="and">and</word>
  <word wid="80" pos="DT" lemma="the">the</word>
  <word wid="81" pos="NNS" lemma="humanities">Humanities</word>
  <word wid="82" pos="NN" lemma="ach">ACH</word>
  <word wid="83" pos="JJ" lemma="canadian">Canadian</word>
  <word wid="84" pos="NN" lemma="society">Society</word>
  <word wid="85" pos="IN" lemma="for">for</word>
  <word wid="86" pos="NNP" lemma="Digital">Digital</word>
  <word wid="87" pos="NNS" lemma="humanities">Humanities</word>
  <word wid="88" pos="NN" lemma="soci">Soci</word>
  <word wid="89" pos="NN" lemma="t">t</word>
  <word wid="90" pos="NNP" lemma="canadienne">canadienne</word>
  <word wid="91" pos="NNP" lemma="des">des</word>
  <word wid="92" pos="NNP" lemma="humanit">humanit</word>
  <word wid="93" pos="NNP" lemma="s">s</word>
  <word wid="94" pos="NNP" lemma="num">num</word>
  <word wid="95" pos="VBZ" lemma="rique">riques</word>
  <word wid="96" pos="NN" lemma="csdh">CSDH</word>
  <word wid="97" pos="NN" lemma="schn">SCHN</word>
  <word wid="98" pos="NNP" lemma="centerNet">centerNet</word>
  <word wid="99" pos="NNP" lemma="Australasian">Australasian</word>
  <word wid="100" pos="NNP" lemma="Association">Association</word>
  <word wid="101" pos="IN" lemma="for">for</word>
  <word wid="102" pos="NNP" lemma="Digital">Digital</word>
  <word wid="103" pos="NNS" lemma="humanities">Humanities</word>
  <word wid="104" pos="VBP" lemma="aadh">aaDH</word>
  <word wid="105" pos="JJ" lemma="japanese">Japanese</word>
  <word wid="106" pos="NN" lemma="association">Association</word>
  <word wid="107" pos="IN" lemma="for">for</word>
  <word wid="108" pos="NNP" lemma="Digital">Digital</word>
  <word wid="109" pos="NNP" lemma="Humanites">Humanites</word>
  <word wid="110" pos="NNP" lemma="JADH">JADH</word>
  <word wid="111" pos="NNP" lemma="Humanistica">Humanistica</word>
  <word wid="112" pos="NNP" lemma="L">L</word>
  <word wid="113" pos="NNP" lemma="association">association</word>
  <word wid="114" pos="NNP" lemma="francophone">francophone</word>
  <word wid="115" pos="NNP" lemma="des">des</word>
  <word wid="116" pos="NNP" lemma="humanit">humanit</word>
  <word wid="117" pos="NNP" lemma="s">s</word>
  <word wid="118" pos="NNP" lemma="num">num</word>
  <word wid="119" pos="NNP" lemma="riques">riques</word>
  <word wid="120" pos="NNP" lemma="digitales">digitales</word>
  <word wid="121" pos="NNP" lemma="Humanistica">Humanistica</word>
  <word wid="122" pos="NNP" lemma="News">News</word>
  <word wid="123" pos="NN" lemma="implementation">Implementation</word>
  <word wid="124" pos="NN" lemma="committee">Committee</word>
  <word wid="125" pos="VBD" lemma="propose">Proposed</word>
  <word wid="126" pos="NNS" lemma="sig">SIGs</word>
  <word wid="127" pos="JJ" lemma="associate">Associate</word>
  <word wid="128" pos="CC" lemma="and">and</word>
  <word wid="129" pos="NN" lemma="affiliate">Affiliate</word>
  <word wid="130" pos="NN" lemma="organization">Organization</word>
  <word wid="131" pos="NNS" lemma="recommendation">Recommendations</word>
  <word wid="132" pos="IN" lemma="as">As</word>
  <word wid="133" pos="NN" lemma="part">part</word>
  <word wid="134" pos="IN" lemma="of">of</word>
  <word wid="135" pos="NN" lemma="adho">ADHO</word>
  <word wid="136" pos="NNS" lemma="s">s</word>
  <word wid="137" pos="JJ" lemma="official">official</word>
  <word wid="138" pos="NN" lemma="change">change</word>
  <word wid="139" pos="TO" lemma="to">to</word>
  <word wid="140" pos="DT" lemma="the">the</word>
  <word wid="141" pos="JJ" lemma="new">new</word>
  <word wid="142" pos="NN" lemma="structure">structure</word>
  <word wid="143" pos="DT" lemma="the">the</word>
  <word wid="144" pos="NN" lemma="implementation">Implementation</word>
  <word wid="145" pos="NN" lemma="committee">Committee</word>
  <word wid="146" pos="NN" lemma="ic">IC</word>
  <word wid="147" pos="VBZ" lemma="have">has</word>
  <word wid="148" pos="RB" lemma="already">already</word>
  <word wid="149" pos="VBN" lemma="suggest">suggested</word>
  <word wid="150" pos="DT" lemma="a">a</word>
  <word wid="151" pos="NN" lemma="draft">draft</word>
  <word wid="152" pos="NN" lemma="roadmap">roadmap</word>
  <word wid="153" pos="DT" lemma="the">the</word>
  <word wid="154" pos="NN" lemma="ic">IC</word>
  <word wid="155" pos="VBZ" lemma="have">has</word>
  <word wid="156" pos="RB" lemma="also">also</word>
  <word wid="157" pos="VBN" lemma="publish">published</word>
  <word wid="158" pos="DT" lemma="the">the</word>
  <word wid="159" pos="VBN" lemma="propose">Proposed</word>
  <word wid="160" pos="JJ" lemma="financial">Financial</word>
  <word wid="161" pos="NNS" lemma="scenario">Scenarios</word>
  <word wid="162" pos="DT" lemma="the">the</word>
  <word wid="163" pos="VBN" lemma="propose">Proposed</word>
  <word wid="164" pos="NN" lemma="governance">Governance</word>
  <word wid="165" pos="NNS" lemma="scenario">Scenarios</word>
  <word wid="166" pos="NN" lemma="version">version</word>
  <word wid="167" pos="CD" lemma="1">1</word>
  <word wid="168" pos="CD" lemma="5">5</word>
  <word wid="169" pos="VBD" lemma="read">Read</word>
  <word wid="170" pos="JJR" lemma="more">more</word>
  <word wid="171" pos="NN" lemma="implementation">Implementation</word>
  <word wid="172" pos="NN" lemma="committee">Committee</word>
  <word wid="173" pos="VBD" lemma="propose">Proposed</word>
  <word wid="174" pos="NNP" lemma="ADHO">ADHO</word>
  <word wid="175" pos="NNP" lemma="Committee">Committee</word>
  <word wid="176" pos="NNS" lemma="recommendation">Recommendations</word>
  <word wid="177" pos="IN" lemma="as">As</word>
  <word wid="178" pos="NN" lemma="part">part</word>
  <word wid="179" pos="IN" lemma="of">of</word>
  <word wid="180" pos="NN" lemma="adho">ADHO</word>
  <word wid="181" pos="NNS" lemma="s">s</word>
  <word wid="182" pos="JJ" lemma="official">official</word>
  <word wid="183" pos="NN" lemma="change">change</word>
  <word wid="184" pos="TO" lemma="to">to</word>
  <word wid="185" pos="DT" lemma="the">the</word>
  <word wid="186" pos="JJ" lemma="new">new</word>
  <word wid="187" pos="NN" lemma="structure">structure</word>
  <word wid="188" pos="DT" lemma="the">the</word>
  <word wid="189" pos="NN" lemma="implementation">Implementation</word>
  <word wid="190" pos="NN" lemma="committee">Committee</word>
  <word wid="191" pos="NN" lemma="ic">IC</word>
  <word wid="192" pos="VBZ" lemma="have">has</word>
  <word wid="193" pos="RB" lemma="already">already</word>
  <word wid="194" pos="VBN" lemma="suggest">suggested</word>
  <word wid="195" pos="DT" lemma="a">a</word>
  <word wid="196" pos="NN" lemma="draft">draft</word>
  <word wid="197" pos="NN" lemma="roadmap">roadmap</word>
  <word wid="198" pos="DT" lemma="the">the</word>
  <word wid="199" pos="NN" lemma="ic">IC</word>
  <word wid="200" pos="VBZ" lemma="have">has</word>
  <word wid="201" pos="RB" lemma="also">also</word>
  <word wid="202" pos="VBN" lemma="publish">published</word>
  <word wid="203" pos="DT" lemma="the">the</word>
  <word wid="204" pos="VBN" lemma="propose">Proposed</word>
  <word wid="205" pos="JJ" lemma="financial">Financial</word>
  <word wid="206" pos="NNS" lemma="scenario">Scenarios</word>
  <word wid="207" pos="DT" lemma="the">the</word>
  <word wid="208" pos="VBN" lemma="propose">Proposed</word>
  <word wid="209" pos="NN" lemma="governance">Governance</word>
  <word wid="210" pos="NNS" lemma="scenario">Scenarios</word>
  <word wid="211" pos="NN" lemma="version">version</word>
  <word wid="212" pos="CD" lemma="1">1</word>
  <word wid="213" pos="CD" lemma="5">5</word>
  <word wid="214" pos="CC" lemma="and">and</word>
  <word wid="215" pos="DT" lemma="the">the</word>
  <word wid="216" pos="NN" lemma="read">Read</word>
  <word wid="217" pos="RBR" lemma="more">more</word>
  <word wid="218" pos="NN" lemma="image">image</word>
  <word wid="219" pos="VBP" lemma="subscribe">Subscribe</word>
  <word wid="220" pos="TO" lemma="to">to</word>
  <word wid="221" pos="NNP" lemma="ADHO">ADHO</word>
  <word wid="222" pos="NNP" lemma="news">news</word>
  <word wid="223" pos="VB" lemma="follow">Follow</word>
  <word wid="224" pos="PRP" lemma="we">us</word>
  <word wid="225" pos="IN" lemma="on">on</word>
  <word wid="226" pos="NNP" lemma="Google">Google</word>
  <word wid="227" pos="NNP" lemma="Facebook">Facebook</word>
  <word wid="228" pos="NNP" lemma="Twitter">Twitter</word>
  <word wid="229" pos="NNP" lemma="YouTube">YouTube</word>
  <word wid="230" pos="NNP" lemma="Event">Event</word>
  <word wid="231" pos="NN" lemma="calendar">Calendar</word>
  <word wid="232" pos="NN" lemma="search">Search</word>
  <word wid="233" pos="NN" lemma="form">form</word>
  <word wid="234" pos="NN" lemma="search">Search</word>
  <word wid="235" pos="NN" lemma="advance">Advance</word>
  <word wid="236" pos="NN" lemma="issue">Issue</word>
  <word wid="237" pos="IN" lemma="of">of</word>
  <word wid="238" pos="NNP" lemma="Digital">Digital</word>
  <word wid="239" pos="NN" lemma="scholarship">Scholarship</word>
  <word wid="240" pos="IN" lemma="in">in</word>
  <word wid="241" pos="DT" lemma="the">the</word>
  <word wid="242" pos="NNS" lemma="humanities">Humanities</word>
  <word wid="243" pos="RB" lemma="formerly">formerly</word>
  <word wid="244" pos="NNP" lemma="LLC">LLC</word>
  <word wid="245" pos="NNP" lemma="Digital">Digital</word>
  <word wid="246" pos="NNS" lemma="humanities">Humanities</word>
  <word wid="247" pos="IN" lemma="in">in</word>
  <word wid="248" pos="NNP" lemma="Poland">Poland</word>
  <word wid="249" pos="IN" lemma="from">from</word>
  <word wid="250" pos="DT" lemma="the">the</word>
  <word wid="251" pos="NN" lemma="perspective">Perspective</word>
  <word wid="252" pos="IN" lemma="of">of</word>
  <word wid="253" pos="DT" lemma="the">the</word>
  <word wid="254" pos="JJ" lemma="historical">Historical</word>
  <word wid="255" pos="NN" lemma="linguist">Linguist</word>
  <word wid="256" pos="IN" lemma="of">of</word>
  <word wid="257" pos="DT" lemma="the">the</word>
  <word wid="258" pos="JJ" lemma="polish">Polish</word>
  <word wid="259" pos="NN" lemma="language">Language</word>
  <word wid="260" pos="NNS" lemma="achievement">Achievements</word>
  <word wid="261" pos="VBZ" lemma="need">Needs</word>
  <word wid="262" pos="NNS" lemma="demand">Demands</word>
  <word wid="263" pos="VBG" lemma="attest">Attesting</word>
  <word wid="264" pos="NN" lemma="similarity">similarity</word>
  <word wid="265" pos="VBG" lemma="support">Supporting</word>
  <word wid="266" pos="DT" lemma="the">the</word>
  <word wid="267" pos="NN" lemma="organization">organization</word>
  <word wid="268" pos="CC" lemma="and">and</word>
  <word wid="269" pos="NN" lemma="study">study</word>
  <word wid="270" pos="IN" lemma="of">of</word>
  <word wid="271" pos="NN" lemma="art">art</word>
  <word wid="272" pos="NN" lemma="image">image</word>
  <word wid="273" pos="NNS" lemma="collection">collections</word>
  <word wid="274" pos="IN" lemma="with">with</word>
  <word wid="275" pos="NN" lemma="computer">computer</word>
  <word wid="276" pos="NN" lemma="vision">vision</word>
  <word wid="277" pos="NN" lemma="rho">Rho</word>
  <word wid="278" pos="NNS" lemma="gram">grams</word>
  <word wid="279" pos="CC" lemma="and">and</word>
  <word wid="280" pos="NN" lemma="rho">rho</word>
  <word wid="281" pos="NNS" lemma="set">sets</word>
  <word wid="282" pos="JJ" lemma="significant">Significant</word>
  <word wid="283" pos="NNS" lemma="link">links</word>
  <word wid="284" pos="IN" lemma="in">in</word>
  <word wid="285" pos="DT" lemma="the">the</word>
  <word wid="286" pos="NN" lemma="web">web</word>
  <word wid="287" pos="IN" lemma="of">of</word>
  <word wid="288" pos="NNS" lemma="word">words</word>
  <word wid="289" pos="NN" lemma="advance">Advance</word>
  <word wid="290" pos="NN" lemma="issue">Issue</word>
  <word wid="291" pos="IN" lemma="of">of</word>
  <word wid="292" pos="NNP" lemma="Digital">Digital</word>
  <word wid="293" pos="NNS" lemma="humanities">Humanities</word>
  <word wid="294" pos="JJ" lemma="quarterly">Quarterly</word>
  <word wid="295" pos="NN" lemma="dhq">DHQ</word>
  <word wid="296" pos="NN" lemma="preview">Preview</word>
  <word wid="297" pos="NN" lemma="author">Author</word>
  <word wid="298" pos="NNS" lemma="biography">Biographies</word>
  <word wid="299" pos="JJ" lemma="introducci">Introducci</word>
  <word wid="300" pos="NN" lemma="n">n</word>
  <word wid="301" pos="IN" lemma="de">de</word>
  <word wid="302" pos="NNP" lemma="los">los</word>
  <word wid="303" pos="NNP" lemma="editoresEditors">editoresEditors</word>
  <word wid="304" pos="NN" lemma="introduction">Introduction</word>
  <word wid="305" pos="NN" lemma="cartograf">Cartograf</word>
  <word wid="306" pos="IN" lemma="as">as</word>
  <word wid="307" pos="FW" lemma="de">de</word>
  <word wid="308" pos="FW" lemma="la">la</word>
  <word wid="309" pos="FW" lemma="sociedad">sociedad</word>
  <word wid="310" pos="NNS" lemma="redcartography">redCartographies</word>
  <word wid="311" pos="IN" lemma="of">of</word>
  <word wid="312" pos="DT" lemma="the">the</word>
  <word wid="313" pos="NN" lemma="network">Network</word>
  <word wid="314" pos="NN" lemma="society">Society</word>
  <word wid="315" pos="NNP" lemma="Laboratorios">Laboratorios</word>
  <word wid="316" pos="NNP" lemma="ciudadanos">ciudadanos</word>
  <word wid="317" pos="NN" lemma="y">y</word>
  <word wid="318" pos="NNS" lemma="humanidade">humanidades</word>
  <word wid="319" pos="JJ" lemma="digitalescitizen">digitalesCitizen</word>
  <word wid="320" pos="NNS" lemma="laboratory">Laboratories</word>
  <word wid="321" pos="CC" lemma="and">and</word>
  <word wid="322" pos="NNP" lemma="Digital">Digital</word>
  <word wid="323" pos="NNS" lemma="humanities">Humanities</word>
  <word wid="324" pos="NN" lemma="image">image</word>
  <word wid="325" pos="NN" lemma="adho">ADHO</word>
  <word wid="326" pos="NN" lemma="logo">logo</word>
  <word wid="327" pos="NN" lemma="adho">ADHO</word>
  <word wid="328" pos="NN" lemma="constituent">Constituent</word>
  <word wid="329" pos="NNS" lemma="organization">Organizations</word>
  <word wid="330" pos="DT" lemma="the">The</word>
  <word wid="331" pos="NNP" lemma="European">European</word>
  <word wid="332" pos="NNP" lemma="Association">Association</word>
  <word wid="333" pos="IN" lemma="for">for</word>
  <word wid="334" pos="NNP" lemma="Digital">Digital</word>
  <word wid="335" pos="NNS" lemma="humanities">Humanities</word>
  <word wid="336" pos="NNP" lemma="EADH">EADH</word>
  <word wid="337" pos="NNP" lemma="Association">Association</word>
  <word wid="338" pos="IN" lemma="for">for</word>
  <word wid="339" pos="NNS" lemma="computer">Computers</word>
  <word wid="340" pos="CC" lemma="and">and</word>
  <word wid="341" pos="DT" lemma="the">the</word>
  <word wid="342" pos="NNS" lemma="humanities">Humanities</word>
  <word wid="343" pos="NN" lemma="ach">ACH</word>
  <word wid="344" pos="JJ" lemma="canadian">Canadian</word>
  <word wid="345" pos="NN" lemma="society">Society</word>
  <word wid="346" pos="IN" lemma="for">for</word>
  <word wid="347" pos="NNP" lemma="Digital">Digital</word>
  <word wid="348" pos="NNS" lemma="humanities">Humanities</word>
  <word wid="349" pos="NN" lemma="soci">Soci</word>
  <word wid="350" pos="NN" lemma="t">t</word>
  <word wid="351" pos="NNP" lemma="canadienne">canadienne</word>
  <word wid="352" pos="NNP" lemma="des">des</word>
  <word wid="353" pos="NNP" lemma="humanit">humanit</word>
  <word wid="354" pos="NNP" lemma="s">s</word>
  <word wid="355" pos="NNP" lemma="num">num</word>
  <word wid="356" pos="VBZ" lemma="rique">riques</word>
  <word wid="357" pos="NN" lemma="csdh">CSDH</word>
  <word wid="358" pos="NN" lemma="schn">SCHN</word>
  <word wid="359" pos="NNP" lemma="centerNet">centerNet</word>
  <word wid="360" pos="NNP" lemma="Australasian">Australasian</word>
  <word wid="361" pos="NNP" lemma="Association">Association</word>
  <word wid="362" pos="IN" lemma="for">for</word>
  <word wid="363" pos="NNP" lemma="Digital">Digital</word>
  <word wid="364" pos="NNS" lemma="humanities">Humanities</word>
  <word wid="365" pos="VBP" lemma="aadh">aaDH</word>
  <word wid="366" pos="JJ" lemma="japanese">Japanese</word>
  <word wid="367" pos="NN" lemma="association">Association</word>
  <word wid="368" pos="IN" lemma="for">for</word>
  <word wid="369" pos="NNP" lemma="Digital">Digital</word>
  <word wid="370" pos="NNS" lemma="humanities">Humanities</word>
  <word wid="371" pos="VBP" lemma="jadh">JADH</word>
  <word wid="372" pos="NNP" lemma="Humanistica">Humanistica</word>
  <word wid="373" pos="NNP" lemma="L">L</word>
  <word wid="374" pos="NNP" lemma="association">association</word>
  <word wid="375" pos="NNP" lemma="francophone">francophone</word>
  <word wid="376" pos="NNP" lemma="des">des</word>
  <word wid="377" pos="NNP" lemma="humanit">humanit</word>
  <word wid="378" pos="NNP" lemma="s">s</word>
  <word wid="379" pos="NNP" lemma="num">num</word>
  <word wid="380" pos="NNP" lemma="riques">riques</word>
  <word wid="381" pos="NNP" lemma="digitales">digitales</word>
  <word wid="382" pos="NNP" lemma="Humanistica">Humanistica</word>
  <word wid="383" pos="NN" lemma="contact">Contact</word>
  <word wid="384" pos="NN" lemma="contact">Contact</word>
  <word wid="385" pos="NN" lemma="form">form</word>
  <word wid="386" pos="NN" lemma="email">Email</word>
  <word wid="387" pos="NN" lemma="web">web</word>
  <word wid="388" pos="NNS" lemma="digitalhumanity">digitalhumanities</word>
  <word wid="389" pos="RB" lemma="org">org</word>
  <word wid="390" pos="NNP" lemma="Google">Google</word>
  <word wid="391" pos="NNP" lemma="Facebook">Facebook</word>
  <word wid="392" pos="NNP" lemma="Twitter">Twitter</word>
  <word wid="393" pos="NNP" lemma="YouTube">YouTube</word>
  <word wid="394" pos="NNS" lemma="event">Events</word>
  <word wid="395" pos="NN" lemma="calendar">Calendar</word>
  <word wid="396" pos="NN" lemma="image">image</word>
  <word wid="397" pos="JJ" lemma="creative">Creative</word>
  <word wid="398" pos="NNPS" lemma="Commons">Commons</word>
  <word wid="399" pos="NN" lemma="attribution">Attribution</word>
  <word wid="400" pos="NN" lemma="license">License</word>
  <word wid="401" pos="DT" lemma="this">This</word>
  <word wid="402" pos="NN" lemma="work">work</word>
  <word wid="403" pos="VBZ" lemma="be">is</word>
  <word wid="404" pos="VBN" lemma="license">licensed</word>
  <word wid="405" pos="IN" lemma="under">under</word>
  <word wid="406" pos="DT" lemma="a">a</word>
  <word wid="407" pos="JJ" lemma="creative">Creative</word>
  <word wid="408" pos="NNP" lemma="Commons">Commons</word>
  <word wid="409" pos="NN" lemma="attribution">Attribution</word>
  <word wid="410" pos="CD" lemma="3">3</word>
  <word wid="411" pos="CD" lemma="0">0</word>
  <word wid="412" pos="JJ" lemma="unported">Unported</word>
  <word wid="413" pos="NN" lemma="license">License</word>
</sentence>
</pos>
