<ner>NYTimes com no longer supports Internet Explorer 9 or earlier Please upgrade your browser LEARN MORE Sections Home Search Skip to content Skip to navigation View mobile version The <ORGANIZATION>New York Times</ORGANIZATION> Books What Is the Best Work of American Fiction of the Last 25 Years Search Subscribe Now Log In 0 Settings Close search Site Search Navigation Search NYTimes com Clear this text input Go Loading See next articles See previous articles Site Navigation Site Mobile Navigation Advertisement Supported by Books What Is the Best Work of American Fiction of the Last 25 Years By THE <LOCATION>NEW YORK</LOCATION> <ORGANIZATION>TIMESMAY</ORGANIZATION> 21 2006 Continue reading the main story Share This Page Continue reading the main story Photo image Beloved by <PERSON>Toni Morrison</PERSON> center was chosen as the best American fiction of the last 25 years Runners up were from left <PERSON>Philip Roth Cormac McCarthy John Updike</PERSON> and <PERSON>Don DeLillo Credit From</PERSON> left <PERSON>Sara Krulwich</PERSON> The <LOCATION>New York</LOCATION> Times <PERSON>Derek Shapton</PERSON> The Associated Press <PERSON>Sara Krulwich</PERSON> The New York Times The Associated Press <PERSON>Don Hogan Charles</PERSON> The <ORGANIZATION>New York Times</ORGANIZATION> THE WINNER THE RUNNERS UP THE FOLLOWING BOOKS ALSO RECEIVED MULTIPLE VOTES Continue reading the main story We re interested in your feedback on this page Tell us what you think Related Coverage Related Coverage What s Next Loading Go to Home Page Site Index The <ORGANIZATION>New York Times Site Index Navigation News World U S Politics N Y Business Tech Science Health Sports Education Obituaries Today</ORGANIZATION> s Paper Corrections Opinion Today s Opinion Op Ed Columnists Editorials Op Ed Contributors Letters Sunday Review Video Opinion Arts Today s Arts Art amp Design Books Dance Movies Music N Y <ORGANIZATION>C Events Guide Television Theater Video Arts Living Automobiles Crossword Food Education Fashion amp Style Health Jobs Magazine N Y C Events Guide Real Estate T Magazine Travel Weddings amp Celebrations Listings amp More Reader Center Classifieds Tools amp Services N Y C Events Guide Multimedia</ORGANIZATION> Photography Video NYT Store Times Journeys Subscribe Manage My Account NYTCo <ORGANIZATION>Subscribe Subscribe Home Delivery Digital Subscriptions Crossword Email Newsletters Alerts Gift Subscriptions Group Subscriptions Education Rate Mobile</ORGANIZATION> Applications Replica Edition Site Information Navigation 2018 The <ORGANIZATION>New York Times Company Home</ORGANIZATION> Search Accessibility concerns Email us at accessibility nytimes com We would love to hear from you Contact Us Work With Us Advertise Your Ad Choices Privacy Terms of Service Terms of Sale Site Information Navigation Site Map Help Site Feedback Subscriptions</ner>
